{
  "system":{
    "description":"Informations about the system such as name, if it is optimized and other relevant information.",
    "name":"C3_TPOB_CHO_H_H-C2_DHPI_NH2_H_H-HCB_A-AA",
    "geo_opt":true,
    "opt_1":true,
    "bomd":true,
    "opt_2":true,
    "DDEC_charges":true,
    "lowdin_charges":true,
    "hirshfeld_charges":true,
    "mulliken_charges":true,
    "textural":true,
    "eqeq_charge":true
  },
  "geometry":{
    "description":"Informations about the geometry: cell parameters, cell matrix, atomic positions, partial charges, bond orders, simmetry information",
    "cell_matrix":[
      [
        44.7727778873,
        0.0,
        0.0
      ],
      [
        22.96762275,
        39.781089532,
        0.0
      ],
      [
        0.0,
        0.0,
        7.8875151137
      ]
    ],
    "cell_parameters":[
      44.7727778873,
      45.9352454999,
      7.8875151137,
      90.0,
      90.0,
      60.0
    ],
    "atom_labels":[
      "H",
      "H",
      "H",
      "H",
      "H",
      "H",
      "H",
      "H",
      "H",
      "H",
      "H",
      "H",
      "H",
      "H",
      "H",
      "H",
      "H",
      "H",
      "H",
      "H",
      "H",
      "H",
      "H",
      "H",
      "H",
      "H",
      "H",
      "H",
      "H",
      "H",
      "H",
      "H",
      "H",
      "H",
      "H",
      "H",
      "H",
      "H",
      "H",
      "H",
      "H",
      "H",
      "H",
      "H",
      "H",
      "H",
      "H",
      "H",
      "H",
      "H",
      "H",
      "H",
      "H",
      "H",
      "H",
      "H",
      "H",
      "H",
      "H",
      "H",
      "H",
      "H",
      "H",
      "H",
      "H",
      "H",
      "H",
      "H",
      "H",
      "H",
      "H",
      "H",
      "H",
      "H",
      "H",
      "H",
      "H",
      "H",
      "H",
      "H",
      "H",
      "H",
      "H",
      "H",
      "H",
      "H",
      "H",
      "H",
      "H",
      "H",
      "H",
      "H",
      "H",
      "H",
      "H",
      "H",
      "H",
      "H",
      "H",
      "H",
      "H",
      "H",
      "H",
      "H",
      "H",
      "H",
      "H",
      "H",
      "C",
      "C",
      "C",
      "C",
      "C",
      "C",
      "C",
      "C",
      "C",
      "C",
      "C",
      "C",
      "C",
      "C",
      "C",
      "C",
      "C",
      "C",
      "C",
      "C",
      "C",
      "C",
      "C",
      "C",
      "C",
      "C",
      "C",
      "C",
      "C",
      "C",
      "C",
      "C",
      "C",
      "C",
      "C",
      "C",
      "C",
      "C",
      "C",
      "C",
      "C",
      "C",
      "C",
      "C",
      "C",
      "C",
      "C",
      "C",
      "C",
      "C",
      "C",
      "C",
      "C",
      "C",
      "C",
      "C",
      "C",
      "C",
      "C",
      "C",
      "C",
      "C",
      "C",
      "C",
      "C",
      "C",
      "C",
      "C",
      "C",
      "C",
      "C",
      "C",
      "C",
      "C",
      "C",
      "C",
      "C",
      "C",
      "C",
      "C",
      "C",
      "C",
      "C",
      "C",
      "C",
      "C",
      "C",
      "C",
      "C",
      "C",
      "C",
      "C",
      "C",
      "C",
      "C",
      "C",
      "C",
      "C",
      "C",
      "C",
      "C",
      "C",
      "C",
      "C",
      "C",
      "C",
      "C",
      "C",
      "C",
      "C",
      "C",
      "C",
      "C",
      "C",
      "C",
      "C",
      "C",
      "C",
      "C",
      "C",
      "C",
      "C",
      "C",
      "C",
      "C",
      "C",
      "C",
      "C",
      "C",
      "C",
      "C",
      "C",
      "C",
      "C",
      "C",
      "C",
      "C",
      "C",
      "C",
      "C",
      "C",
      "C",
      "C",
      "C",
      "C",
      "C",
      "C",
      "C",
      "C",
      "C",
      "C",
      "C",
      "C",
      "C",
      "C",
      "C",
      "C",
      "C",
      "C",
      "C",
      "C",
      "C",
      "C",
      "C",
      "C",
      "C",
      "C",
      "C",
      "N",
      "N",
      "N",
      "N",
      "N",
      "N",
      "N",
      "N",
      "N",
      "N",
      "N",
      "N",
      "N",
      "N",
      "N",
      "N",
      "N",
      "N",
      "N",
      "N",
      "N",
      "N",
      "N",
      "N",
      "O",
      "O",
      "O",
      "O",
      "O",
      "O",
      "O",
      "O",
      "O",
      "O",
      "O",
      "O"
    ],
    "atom_pos":[
      [
        12.0938414862,
        21.5010797979,
        3.4511662061
      ],
      [
        11.6002920877,
        20.9866007943,
        7.1738762561
      ],
      [
        10.917096822,
        17.4716250566,
        0.5859685497
      ],
      [
        10.3044156895,
        17.0843490133,
        4.1838982914
      ],
      [
        20.3613103969,
        -0.1679317087,
        3.2433410371
      ],
      [
        19.7848897265,
        -0.9396508932,
        7.516870646
      ],
      [
        2.3749566607,
        40.7925637382,
        0.0988918468
      ],
      [
        1.8350417576,
        39.9861309318,
        4.4053277093
      ],
      [
        33.7409520061,
        16.9176811689,
        3.210775026
      ],
      [
        33.0889522358,
        16.1150038232,
        7.3006562235
      ],
      [
        31.1506920749,
        19.3259644592,
        0.9957244985
      ],
      [
        30.6758636274,
        18.535606303,
        4.8975450677
      ],
      [
        29.4620387972,
        18.2367104585,
        2.5368914572
      ],
      [
        28.8960430536,
        17.423681747,
        6.2723616028
      ],
      [
        20.0410428735,
        2.8272561376,
        3.2822618176
      ],
      [
        19.4708676858,
        2.0600381666,
        7.5161611615
      ],
      [
        23.0245050222,
        3.558391634,
        0.4059208204
      ],
      [
        22.4357386557,
        2.727271254,
        4.6449766417
      ],
      [
        22.950252016,
        5.636657022,
        0.9014804613
      ],
      [
        22.4188723598,
        4.8366654527,
        5.1575475215
      ],
      [
        17.4458494274,
        15.0755138867,
        -0.2131496451
      ],
      [
        16.7855331573,
        14.3672470523,
        3.5961799539
      ],
      [
        20.6024488059,
        13.5937002255,
        1.590006798
      ],
      [
        19.9671029675,
        12.8417068634,
        5.6160989158
      ],
      [
        19.8448062391,
        14.4598390131,
        -0.4391140834
      ],
      [
        19.1598270422,
        13.6158120736,
        3.5100434662
      ],
      [
        20.9448056212,
        17.8062148811,
        2.0125427452
      ],
      [
        20.3593713235,
        17.1791074596,
        5.591079409
      ],
      [
        18.518502024,
        18.4649370346,
        2.207495359
      ],
      [
        17.9712934484,
        17.9469209513,
        5.6622473798
      ],
      [
        27.2208089355,
        17.3423378584,
        3.1410279276
      ],
      [
        26.6811360486,
        16.6068857714,
        6.8256430011
      ],
      [
        24.3810484443,
        15.4658713415,
        0.6898222593
      ],
      [
        23.7147267921,
        14.6242759953,
        4.4275448684
      ],
      [
        25.4585661574,
        15.6372427452,
        2.8200057481
      ],
      [
        24.8638809914,
        14.9477512929,
        6.509964158
      ],
      [
        28.2320449419,
        13.178464302,
        0.633338936
      ],
      [
        27.598768665,
        12.3260636923,
        4.4865084469
      ],
      [
        30.0484515335,
        14.8536078809,
        1.0598008696
      ],
      [
        29.4508096585,
        13.981830237,
        4.8434408717
      ],
      [
        23.626181255,
        7.8589209134,
        0.5158814159
      ],
      [
        23.0917944502,
        7.0401658288,
        4.7338118371
      ],
      [
        24.2905014034,
        11.534475431,
        2.4586592745
      ],
      [
        23.6920516904,
        10.8249338135,
        6.4618851114
      ],
      [
        23.4242702474,
        10.2900043303,
        0.8762738338
      ],
      [
        22.8975184067,
        9.4696145769,
        5.0091855873
      ],
      [
        20.015016238,
        9.6388078793,
        3.4156030002
      ],
      [
        19.4673050651,
        8.9064508652,
        7.5526577143
      ],
      [
        20.1886975331,
        7.1733981113,
        3.0072657241
      ],
      [
        19.6429845141,
        6.4320195199,
        7.2286602708
      ],
      [
        14.8634727366,
        20.3429396568,
        3.1734607296
      ],
      [
        14.3369080694,
        19.7759631107,
        6.8403088399
      ],
      [
        13.7198514829,
        17.3921913926,
        0.4550459667
      ],
      [
        13.1259889549,
        16.9194364112,
        4.0161492193
      ],
      [
        15.7124279772,
        16.5015254999,
        0.6061899296
      ],
      [
        15.1024539469,
        15.9592984253,
        4.2088304081
      ],
      [
        -12.2091933532,
        21.7624515384,
        0.8294303505
      ],
      [
        -12.6430294778,
        20.9396913516,
        4.7877453504
      ],
      [
        36.0187243324,
        18.8817700253,
        3.1969184499
      ],
      [
        35.3649831742,
        18.0758108792,
        7.4634391768
      ],
      [
        -9.9114576233,
        23.7047950264,
        0.7592582206
      ],
      [
        -10.3041961683,
        22.8124037151,
        4.7576746567
      ],
      [
        -7.3145667589,
        21.3127128208,
        2.9726307111
      ],
      [
        -7.8899331264,
        20.4788346087,
        7.2481297892
      ],
      [
        -5.6627025085,
        22.251245239,
        1.3777043919
      ],
      [
        -6.1351613275,
        21.266978443,
        5.5613891582
      ],
      [
        2.7381464587,
        37.8050510548,
        0.1228398924
      ],
      [
        2.202505588,
        37.0052992434,
        4.4545003196
      ],
      [
        -0.1744139834,
        37.1188920432,
        3.0307667973
      ],
      [
        -0.8142975118,
        36.2992931454,
        7.288838595
      ],
      [
        -0.0608082475,
        34.976020828,
        2.6097375039
      ],
      [
        -0.7179997076,
        34.1147374395,
        6.7231983162
      ],
      [
        6.026957187,
        24.5787220584,
        1.1235802634
      ],
      [
        5.3496199924,
        24.0342339594,
        5.2901213441
      ],
      [
        3.0782596642,
        27.0698155297,
        2.9593007286
      ],
      [
        2.2915873755,
        26.4632338934,
        7.2047407165
      ],
      [
        3.8441934197,
        25.6836909629,
        1.4288168305
      ],
      [
        3.1498603408,
        25.0652551568,
        5.6510352779
      ],
      [
        2.4580236789,
        22.3116720053,
        3.7153071092
      ],
      [
        1.9925196434,
        21.7474904195,
        8.1339307229
      ],
      [
        4.6380388158,
        21.1455413186,
        3.3142744477
      ],
      [
        4.1931731211,
        20.6403440241,
        7.6690712553
      ],
      [
        -3.4835206412,
        22.8579740044,
        0.5078025278
      ],
      [
        -4.0120712819,
        21.8309448544,
        4.3949489734
      ],
      [
        -0.5028555666,
        24.8737568773,
        2.0071929972
      ],
      [
        -1.0135134418,
        24.0123872797,
        5.9254084938
      ],
      [
        -1.6427439191,
        24.5035357542,
        0.2480200837
      ],
      [
        -2.191300765,
        23.4631703133,
        3.9084086193
      ],
      [
        -4.1193489472,
        27.564841162,
        1.9548691672
      ],
      [
        -4.4174699692,
        26.5453549165,
        5.9006845051
      ],
      [
        -6.0235082762,
        25.9283153641,
        2.1208373842
      ],
      [
        -6.3152266815,
        24.9432036512,
        6.2781812189
      ],
      [
        -0.469073783,
        32.7219406591,
        3.2214607888
      ],
      [
        -1.2447932295,
        31.7836281803,
        6.9725643079
      ],
      [
        -0.2305697166,
        29.0886201552,
        1.0792435609
      ],
      [
        -0.7028467465,
        28.0974330916,
        4.561237118
      ],
      [
        0.1333975258,
        30.3209500765,
        3.2323894324
      ],
      [
        -0.6766670527,
        29.3781126242,
        6.7302429588
      ],
      [
        3.4414769377,
        31.1367059121,
        0.6084115858
      ],
      [
        3.138676645,
        30.4523291047,
        5.061681463
      ],
      [
        2.8489404461,
        33.5771756128,
        0.6245144038
      ],
      [
        2.5396454034,
        32.8820176177,
        5.2544827813
      ],
      [
        8.1467293543,
        18.5924962182,
        0.8930203617
      ],
      [
        7.5481721065,
        18.1803787352,
        4.6783542405
      ],
      [
        9.2595466013,
        21.6736944549,
        3.491001711
      ],
      [
        8.798807439,
        21.1701093953,
        7.2930247836
      ],
      [
        7.6168317628,
        22.864500614,
        1.7628488727
      ],
      [
        7.0160189229,
        22.4068498352,
        5.8701025715
      ],
      [
        11.8409653547,
        20.6300375958,
        2.8531335298
      ],
      [
        11.326300479,
        20.1628652195,
        6.518225338
      ],
      [
        12.8257358831,
        19.7168359393,
        2.4315204127
      ],
      [
        12.2886246875,
        19.248185171,
        6.0493981497
      ],
      [
        12.4637176449,
        18.5823968606,
        1.627450756
      ],
      [
        11.8980512886,
        18.1578416367,
        5.195244253
      ],
      [
        11.163133636,
        18.3185820019,
        1.2218202078
      ],
      [
        10.5823721242,
        17.921191708,
        4.8182493484
      ],
      [
        10.1751506673,
        19.2227388297,
        1.6549597316
      ],
      [
        9.616941691,
        18.8211038952,
        5.3092712695
      ],
      [
        10.5429244805,
        20.3701928388,
        2.4392523976
      ],
      [
        10.0198064682,
        19.9456534164,
        6.1091627263
      ],
      [
        21.1666233588,
        0.0860754012,
        2.5584661258
      ],
      [
        20.60590013,
        -0.6958940092,
        6.8482070894
      ],
      [
        21.4519477778,
        1.4245158388,
        2.219842571
      ],
      [
        20.8996885886,
        0.6373179508,
        6.5020169165
      ],
      [
        22.5459093714,
        1.7301916244,
        1.3371859186
      ],
      [
        22.0151355417,
        0.9357813617,
        5.6445002304
      ],
      [
        1.5596396398,
        40.54200284,
        0.7715579542
      ],
      [
        1.0195281392,
        39.7424587926,
        5.0815545336
      ],
      [
        1.2786883529,
        39.208992721,
        1.119829809
      ],
      [
        0.7305372193,
        38.4090457635,
        5.4317119626
      ],
      [
        0.1760908803,
        38.8999943359,
        1.9898109962
      ],
      [
        -0.3738449998,
        38.1079374839,
        6.3034884735
      ],
      [
        33.3258792708,
        17.7877724341,
        2.7182424255
      ],
      [
        32.7126784538,
        16.9872188413,
        6.7813168395
      ],
      [
        29.7997426916,
        17.2091282281,
        2.3257976292
      ],
      [
        29.2398276658,
        16.3943672809,
        6.0879331932
      ],
      [
        32.0198476383,
        17.8820670539,
        2.2611371501
      ],
      [
        31.4505710526,
        17.074966722,
        6.211330808
      ],
      [
        20.8657337737,
        2.6675575516,
        2.5973926302
      ],
      [
        20.3008290158,
        1.8867449308,
        6.8427212778
      ],
      [
        22.1098843281,
        5.9135972076,
        1.5551005615
      ],
      [
        21.5635181792,
        5.1220890655,
        5.7881029086
      ],
      [
        21.5697723329,
        3.6901669305,
        1.9648951821
      ],
      [
        21.0198906443,
        2.8993764733,
        6.2189276772
      ],
      [
        18.2060047304,
        15.6728320022,
        0.2874008192
      ],
      [
        17.5672051209,
        14.9864785197,
        4.0356748656
      ],
      [
        21.6849282733,
        13.571486463,
        1.5563065523
      ],
      [
        21.051013468,
        12.8293661642,
        5.5771011356
      ],
      [
        19.5479730093,
        15.3138605703,
        0.1638028526
      ],
      [
        18.8970620231,
        14.5564483035,
        3.9870269006
      ],
      [
        22.430847803,
        14.656655589,
        1.0962758503
      ],
      [
        21.78483132,
        13.8855587219,
        5.030331719
      ],
      [
        17.8216052764,
        16.8137343541,
        1.0162013078
      ],
      [
        17.2142815035,
        16.2044782247,
        4.6493189777
      ],
      [
        20.1593684866,
        17.2270958306,
        1.5349113393
      ],
      [
        19.5625185069,
        16.5872226458,
        5.1473155996
      ],
      [
        18.8225657097,
        17.5888737349,
        1.6388746287
      ],
      [
        18.2415987678,
        17.0067630755,
        5.1879023734
      ],
      [
        20.5168769091,
        16.0937764734,
        0.7968211772
      ],
      [
        19.8874401102,
        15.3548646709,
        4.5687842908
      ],
      [
        27.4537229484,
        16.42743452,
        2.5985484168
      ],
      [
        26.887078329,
        15.6739939126,
        6.3022263795
      ],
      [
        23.8286181257,
        14.6085782697,
        1.0572868336
      ],
      [
        23.1805307907,
        13.8232422695,
        4.9275719643
      ],
      [
        26.451213193,
        15.4763252885,
        2.4111159452
      ],
      [
        25.8600883919,
        14.7485391608,
        6.1313241115
      ],
      [
        24.4722229056,
        13.4635251703,
        1.5253925856
      ],
      [
        23.839663562,
        12.7196001003,
        5.4581156055
      ],
      [
        28.763644839,
        16.209661967,
        2.1304580734
      ],
      [
        28.1963343699,
        15.4070982968,
        5.8613873071
      ],
      [
        28.0415382421,
        14.0806123863,
        1.2091589732
      ],
      [
        27.4238084922,
        13.2623985912,
        5.0106999366
      ],
      [
        29.0429474389,
        15.010402505,
        1.4439877275
      ],
      [
        28.4464737327,
        14.1816034832,
        5.2110460941
      ],
      [
        26.745741801,
        14.3106425111,
        1.696302842
      ],
      [
        26.1320641237,
        13.5401488027,
        5.4862500663
      ],
      [
        22.8375039879,
        8.2395921605,
        1.1630727967
      ],
      [
        22.3018649353,
        7.4384178386,
        5.3690067188
      ],
      [
        23.7565674907,
        12.3783041766,
        2.0369358818
      ],
      [
        23.1417848443,
        11.6638340947,
        6.0535463862
      ],
      [
        22.7378496607,
        9.6134774304,
        1.3719916814
      ],
      [
        22.2053992354,
        8.8209144982,
        5.5335816806
      ],
      [
        22.3621799801,
        12.4422795284,
        2.0186606144
      ],
      [
        21.7462500531,
        11.7080739817,
        6.0532713193
      ],
      [
        21.9366011675,
        7.3387531562,
        1.7600316849
      ],
      [
        21.3897213576,
        6.5530591625,
        5.970356156
      ],
      [
        20.7948601935,
        9.2296380394,
        2.7781968953
      ],
      [
        20.2512406539,
        8.4781362808,
        6.9332571825
      ],
      [
        20.8949924158,
        7.8640586893,
        2.5521120092
      ],
      [
        20.3502532454,
        7.106462247,
        6.750932188
      ],
      [
        21.7327774638,
        10.1065635191,
        2.2093937662
      ],
      [
        21.1838924395,
        9.3435246238,
        6.332137465
      ],
      [
        14.2411204927,
        19.6715735159,
        2.5957087665
      ],
      [
        13.6979355087,
        19.1464306005,
        6.23200938
      ],
      [
        16.4169555812,
        17.1717228853,
        1.1194210078
      ],
      [
        15.8192181969,
        16.6086939923,
        4.7327559759
      ],
      [
        14.7246019726,
        18.5711120706,
        1.9000403732
      ],
      [
        14.1537717067,
        18.057676264,
        5.4940356388
      ],
      [
        -11.4725117196,
        21.1525511803,
        1.3459525575
      ],
      [
        -11.9596638847,
        20.3381773927,
        5.381668717
      ],
      [
        -10.1580674574,
        21.6101494536,
        1.5584564048
      ],
      [
        -10.6553903344,
        20.7833836639,
        5.6724513209
      ],
      [
        -9.1941699318,
        20.7615643661,
        2.2057988523
      ],
      [
        -9.7514504343,
        19.9442494287,
        6.4122725483
      ],
      [
        35.2785073395,
        19.4978251551,
        2.692395252
      ],
      [
        34.6682973651,
        18.6949855653,
        6.9045863651
      ],
      [
        33.9659989187,
        19.037741059,
        2.4750763274
      ],
      [
        33.3712708761,
        18.2396549412,
        6.5943178503
      ],
      [
        33.0043656847,
        19.8837035152,
        1.819565239
      ],
      [
        32.4665966991,
        19.08279474,
        5.8587404615
      ],
      [
        -9.5024919427,
        22.8433217983,
        1.2716069875
      ],
      [
        -9.9513526227,
        21.9806124925,
        5.3551720796
      ],
      [
        -5.9533673655,
        23.3105345655,
        1.442103165
      ],
      [
        -6.3956661813,
        22.3370660265,
        5.5516945378
      ],
      [
        -8.1816924164,
        22.7332529673,
        1.6794738196
      ],
      [
        -8.65402598,
        21.8533768961,
        5.833122956
      ],
      [
        1.9020580055,
        37.9709461918,
        0.7900811573
      ],
      [
        1.3518226227,
        37.1703742491,
        5.1054054993
      ],
      [
        0.8148295225,
        34.726986491,
        1.9917475737
      ],
      [
        0.2332011543,
        33.9007983858,
        6.2134286018
      ],
      [
        1.2163425635,
        36.9547636373,
        1.4418011027
      ],
      [
        0.6638038191,
        36.1535136087,
        5.7615693024
      ],
      [
        5.2479115344,
        24.0735839778,
        1.6930039054
      ],
      [
        4.623720424,
        23.5279862416,
        5.9244933177
      ],
      [
        2.0889182602,
        27.0202319057,
        2.518067679
      ],
      [
        1.3888530449,
        26.3264591601,
        6.6188630369
      ],
      [
        4.0201260608,
        24.7100933505,
        1.8712598326
      ],
      [
        3.3838035528,
        24.1239824375,
        6.1333604607
      ],
      [
        1.3470885014,
        25.8396439546,
        2.4627434889
      ],
      [
        0.7118036625,
        25.1096252321,
        6.576867095
      ],
      [
        5.492995655,
        22.7895826654,
        2.2123991693
      ],
      [
        4.9322684757,
        22.2643531756,
        6.4549243863
      ],
      [
        3.2454668517,
        22.7810986942,
        3.1311526923
      ],
      [
        2.7376816235,
        22.2226355094,
        7.5013612388
      ],
      [
        4.4552191144,
        22.1394557779,
        2.9100681057
      ],
      [
        3.9606680854,
        21.6136450448,
        7.2423339839
      ],
      [
        3.0284405442,
        24.075491798,
        2.6272854977
      ],
      [
        2.4439846375,
        23.4743088164,
        6.9364970033
      ],
      [
        -3.6262505155,
        23.8862687528,
        0.8371126418
      ],
      [
        -4.1108269559,
        22.8654607826,
        4.7212616835
      ],
      [
        0.0351063601,
        25.812076332,
        1.9833106404
      ],
      [
        -0.5068274735,
        24.9709498382,
        5.9132488031
      ],
      [
        -2.5824600604,
        24.7993881006,
        0.6994012314
      ],
      [
        -3.080790049,
        23.7703997964,
        4.4527340665
      ],
      [
        -0.5257182224,
        26.9930382061,
        1.4999661362
      ],
      [
        -1.0387549888,
        26.0782703206,
        5.2470805861
      ],
      [
        -4.8761390085,
        24.2809793974,
        1.3445570677
      ],
      [
        -5.2981576943,
        23.2804671281,
        5.3566932854
      ],
      [
        -4.0077937818,
        26.533047392,
        1.6320402755
      ],
      [
        -4.3646309966,
        25.5170579301,
        5.5523440374
      ],
      [
        -5.0549771581,
        25.6253044279,
        1.7292268626
      ],
      [
        -5.4082381768,
        24.624388918,
        5.7689324405
      ],
      [
        -2.7701092593,
        26.1182370373,
        1.1242723515
      ],
      [
        -3.213339392,
        25.0933176847,
        4.8832184468
      ],
      [
        0.3780435168,
        32.3774997325,
        2.6306460672
      ],
      [
        -0.2844146055,
        31.4980377743,
        6.5457984411
      ],
      [
        0.2090911096,
        28.1854519,
        1.4868723182
      ],
      [
        -0.3225903933,
        27.279612014,
        5.1652585203
      ],
      [
        0.707743484,
        31.0232346208,
        2.6361875103
      ],
      [
        0.0293920111,
        30.1433421713,
        6.4206097388
      ],
      [
        1.5030799291,
        28.1849695964,
        2.0001769119
      ],
      [
        0.8829289362,
        27.381468135,
        5.8567524205
      ],
      [
        1.1528797439,
        33.3168599559,
        1.9255442632
      ],
      [
        0.6076045483,
        32.5006919529,
        6.1240789691
      ],
      [
        2.5910686647,
        31.5055926707,
        1.1751014625
      ],
      [
        2.1864661413,
        30.7674663314,
        5.4819541974
      ],
      [
        2.2611785159,
        32.8537901821,
        1.1852077459
      ],
      [
        1.8545698081,
        32.1071990847,
        5.5923674953
      ],
      [
        1.824150391,
        30.5943958614,
        1.9136569619
      ],
      [
        1.2700021085,
        29.7837452098,
        5.8860510166
      ],
      [
        8.7583937516,
        19.2717397926,
        1.4750435183
      ],
      [
        8.1906250137,
        18.8580356589,
        5.2259932611
      ],
      [
        6.7982863734,
        22.1789703826,
        2.033103703
      ],
      [
        6.2289538267,
        21.6862877556,
        6.1433877587
      ],
      [
        8.2945637377,
        20.4237896708,
        2.0921005885
      ],
      [
        7.7533734798,
        19.9803610194,
        5.9115124219
      ],
      [
        31.7930500632,
        19.186653856,
        1.7719564734
      ],
      [
        31.2619427915,
        18.3845081384,
        5.7144159991
      ],
      [
        31.0639947151,
        16.9064170932,
        2.2596539176
      ],
      [
        30.5037250956,
        16.0891891987,
        6.1227905268
      ],
      [
        22.6200513675,
        3.1157835121,
        1.223878009
      ],
      [
        22.1073262098,
        2.3252635555,
        5.521331402
      ],
      [
        21.3453427813,
        5.0275436486,
        2.1263306311
      ],
      [
        20.7849508312,
        4.2404859062,
        6.3506474741
      ],
      [
        13.6296141958,
        17.8521019845,
        1.359734455
      ],
      [
        13.0460811624,
        17.4190496572,
        4.8979181891
      ],
      [
        16.0359057677,
        18.2220768069,
        1.7885424784
      ],
      [
        15.4559616708,
        17.6601301336,
        5.4098497927
      ],
      [
        -7.965594956,
        21.4352250392,
        2.2006550438
      ],
      [
        -8.5097991556,
        20.5907650354,
        6.4488604685
      ],
      [
        -7.1992885498,
        23.6710885909,
        1.5358314098
      ],
      [
        -7.6311935179,
        22.7391993738,
        5.6347244821
      ],
      [
        0.1141777632,
        37.508408812,
        2.1338169178
      ],
      [
        -0.4293792009,
        36.7200572273,
        6.4491939723
      ],
      [
        1.522377763,
        35.6278722898,
        1.3716079136
      ],
      [
        0.9785215885,
        34.8306044974,
        5.6903888336
      ],
      [
        9.3855551954,
        21.1288774258,
        2.640542772
      ],
      [
        8.8727896655,
        20.6981827122,
        6.3925511096
      ],
      [
        7.0071285026,
        20.9008438236,
        2.1513714485
      ],
      [
        6.4641758241,
        20.4087816218,
        6.1157348326
      ],
      [
        21.886679219,
        15.8504607874,
        0.6570841254
      ],
      [
        21.2486579665,
        15.0584496027,
        4.5299141572
      ],
      [
        25.8476656578,
        13.2841302106,
        1.4535638221
      ],
      [
        25.2092032161,
        12.5175393302,
        5.3233931722
      ],
      [
        21.5487488018,
        11.4425041262,
        2.5416471474
      ],
      [
        20.9504930484,
        10.6939726254,
        6.5764739186
      ],
      [
        1.7966113337,
        24.6150081552,
        2.9575325276
      ],
      [
        1.1798439819,
        23.9724113249,
        7.2341843537
      ],
      [
        -1.8063542015,
        27.1174540242,
        0.9868341753
      ],
      [
        -2.2576573439,
        26.0729855106,
        4.5924298353
      ],
      [
        2.3286986718,
        29.2962908927,
        1.9742933157
      ],
      [
        1.7230459382,
        28.4826733837,
        5.7465214835
      ]
    ],
    "energy":-1450.7510133379926,
    "band_gap":1.373535,
    "fermi_level":-2.835547,
    "density":0.31379889819652873,
    "composition":"H108 C168 N24 O12",
    "DDEC_charges":[
      0.1317,
      0.133739,
      0.135782,
      0.132834,
      0.185228,
      0.183941,
      0.183184,
      0.186337,
      0.15668,
      0.157731,
      0.291893,
      0.28317,
      0.062726,
      0.066353,
      0.15894,
      0.155927,
      0.301056,
      0.293902,
      0.062438,
      0.067465,
      0.108479,
      0.10837,
      0.14776,
      0.151871,
      0.12236,
      0.135231,
      0.134484,
      0.13705,
      0.122184,
      0.124704,
      0.104987,
      0.10768,
      0.155169,
      0.153177,
      0.127751,
      0.124051,
      0.1387,
      0.137225,
      0.124264,
      0.126279,
      0.104763,
      0.106273,
      0.161513,
      0.157504,
      0.123872,
      0.128177,
      0.134033,
      0.133313,
      0.119461,
      0.126239,
      0.15437,
      0.156328,
      0.286141,
      0.290306,
      0.06716,
      0.06703,
      0.086346,
      0.086719,
      0.085732,
      0.088395,
      0.154246,
      0.154816,
      0.28455,
      0.28946,
      0.064357,
      0.066489,
      0.158148,
      0.160162,
      0.289923,
      0.300658,
      0.068402,
      0.068304,
      0.107139,
      0.105134,
      0.161963,
      0.155294,
      0.127417,
      0.128555,
      0.135861,
      0.133531,
      0.124408,
      0.123398,
      0.10791,
      0.106221,
      0.151305,
      0.149515,
      0.1272,
      0.133792,
      0.135017,
      0.138988,
      0.124672,
      0.124355,
      0.105313,
      0.107282,
      0.148882,
      0.15533,
      0.123528,
      0.131004,
      0.132965,
      0.137707,
      0.122004,
      0.124303,
      0.159617,
      0.156566,
      0.293125,
      0.285609,
      0.065649,
      0.065029,
      -0.23914,
      -0.236806,
      0.040177,
      0.038329,
      0.172072,
      0.178954,
      -0.246232,
      -0.251084,
      0.054838,
      0.059263,
      0.164684,
      0.159941,
      -0.2403,
      -0.250202,
      0.036906,
      0.042239,
      0.145975,
      0.130895,
      -0.252866,
      -0.24067,
      0.04203,
      0.037794,
      0.125425,
      0.141984,
      -0.288308,
      -0.298454,
      0.07864,
      0.086063,
      0.314835,
      0.320304,
      -0.322485,
      -0.307688,
      0.085918,
      0.082582,
      0.317218,
      0.316207,
      -0.11278,
      -0.115976,
      -0.365013,
      -0.368824,
      -0.204615,
      -0.215012,
      0.337659,
      0.337336,
      0.037326,
      0.033154,
      -0.200816,
      -0.196337,
      -0.08712,
      -0.077238,
      0.267156,
      0.269773,
      -0.109099,
      -0.102522,
      -0.369818,
      -0.356635,
      -0.232085,
      -0.232865,
      0.323163,
      0.323733,
      0.017651,
      0.016537,
      -0.202516,
      -0.207373,
      -0.076007,
      -0.079558,
      0.282589,
      0.29091,
      -0.104862,
      -0.09902,
      -0.359409,
      -0.365598,
      -0.234706,
      -0.235596,
      0.32962,
      0.334259,
      0.017978,
      0.017388,
      -0.207125,
      -0.207323,
      -0.07552,
      -0.080427,
      0.286045,
      0.285003,
      -0.288469,
      -0.302932,
      0.077188,
      0.081534,
      0.307644,
      0.311795,
      -0.222291,
      -0.215809,
      0.054218,
      0.053421,
      0.117472,
      0.134284,
      -0.217568,
      -0.226442,
      0.06249,
      0.060614,
      0.133287,
      0.111259,
      -0.284147,
      -0.27547,
      0.079336,
      0.062088,
      0.314044,
      0.30602,
      -0.306777,
      -0.322989,
      0.080868,
      0.075789,
      0.313266,
      0.315215,
      -0.100117,
      -0.097155,
      -0.366288,
      -0.352203,
      -0.235681,
      -0.235265,
      0.326441,
      0.324553,
      0.009046,
      0.013117,
      -0.204124,
      -0.214258,
      -0.076131,
      -0.075693,
      0.292134,
      0.287846,
      -0.112942,
      -0.12721,
      -0.366993,
      -0.363754,
      -0.215581,
      -0.203836,
      0.339319,
      0.337533,
      0.030728,
      0.036299,
      -0.19799,
      -0.194007,
      -0.085766,
      -0.079909,
      0.280717,
      0.269523,
      -0.10531,
      -0.106964,
      -0.372569,
      -0.35255,
      -0.218382,
      -0.235868,
      0.331911,
      0.317986,
      0.023529,
      0.022539,
      -0.204402,
      -0.205353,
      -0.0788,
      -0.076019,
      0.272905,
      0.284013,
      -0.329076,
      -0.322721,
      0.094241,
      0.098259,
      0.321696,
      0.323299,
      -0.379719,
      -0.382041,
      -0.330048,
      -0.332654,
      -0.411746,
      -0.42199,
      -0.350071,
      -0.349002,
      -0.426648,
      -0.414424,
      -0.342339,
      -0.35096,
      -0.384496,
      -0.375,
      -0.329775,
      -0.318168,
      -0.422492,
      -0.412576,
      -0.344065,
      -0.344923,
      -0.410367,
      -0.419056,
      -0.337227,
      -0.340928,
      -0.259501,
      -0.256841,
      -0.249323,
      -0.252182,
      -0.2564,
      -0.253416,
      -0.25221,
      -0.259021,
      -0.259689,
      -0.264103,
      -0.253919,
      -0.252433
    ],
    "bond_orders":[
      0.978553,
      0.975902,
      0.974295,
      0.980289,
      0.973555,
      0.975861,
      0.977674,
      0.972342,
      0.970782,
      0.971292,
      0.908339,
      0.927729,
      0.981236,
      0.978173,
      0.977298,
      0.978248,
      0.906001,
      0.925004,
      0.986618,
      0.985759,
      0.985593,
      0.982871,
      1.015674,
      0.99562,
      1.014628,
      0.980514,
      0.96839,
      0.964745,
      0.984209,
      0.97695,
      0.985931,
      0.981615,
      0.985749,
      0.986145,
      1.000532,
      1.028711,
      0.966197,
      0.966294,
      0.981031,
      0.970389,
      0.989548,
      0.986597,
      0.970102,
      0.983127,
      1.025045,
      1.011067,
      0.970506,
      0.972887,
      0.983227,
      0.973759,
      0.973987,
      0.975096,
      0.931015,
      0.923847,
      0.985123,
      0.981171,
      1.046202,
      1.049299,
      1.044228,
      1.048414,
      0.973208,
      0.97257,
      0.92602,
      0.915821,
      0.984468,
      0.982887,
      0.974362,
      0.974807,
      0.931616,
      0.904533,
      0.984339,
      0.97662,
      0.981855,
      0.988163,
      0.968406,
      0.980484,
      1.011666,
      1.017656,
      0.967624,
      0.972828,
      0.975527,
      0.97245,
      0.981755,
      0.986815,
      1.006711,
      1.001354,
      1.0221,
      0.972494,
      0.966896,
      0.96206,
      0.975691,
      0.976981,
      0.991634,
      0.98281,
      1.013479,
      0.979979,
      1.004498,
      1.002084,
      0.974205,
      0.964016,
      0.981385,
      0.975095,
      0.975598,
      0.977115,
      0.908883,
      0.926626,
      0.97863,
      0.978347,
      3.999611,
      4.001985,
      4.105211,
      4.110987,
      4.074031,
      4.074103,
      3.998884,
      3.997788,
      4.105706,
      4.096336,
      4.085595,
      4.08056,
      3.27414,
      3.262559,
      4.241517,
      4.251335,
      3.549757,
      3.568214,
      3.274239,
      3.281574,
      4.260538,
      4.246526,
      3.564307,
      3.545018,
      3.908057,
      3.914054,
      3.965644,
      3.963759,
      4.145013,
      4.124357,
      3.934795,
      3.932161,
      3.967851,
      3.962311,
      4.144024,
      4.131454,
      4.001612,
      4.004527,
      3.983028,
      3.96801,
      4.02199,
      4.012412,
      4.055676,
      4.044087,
      4.075539,
      4.072886,
      4.013059,
      4.011396,
      3.961671,
      3.951671,
      4.022495,
      4.027741,
      4.023426,
      4.008823,
      3.986788,
      3.987243,
      4.039951,
      4.027696,
      4.059668,
      4.061478,
      4.095221,
      4.097569,
      3.997473,
      3.996553,
      3.955295,
      3.962197,
      4.036793,
      4.015528,
      4.021215,
      4.009063,
      3.982903,
      3.980215,
      4.035425,
      4.03774,
      4.048172,
      4.042974,
      4.096533,
      4.088733,
      4.003969,
      4.006628,
      3.963565,
      3.959537,
      4.010478,
      4.013536,
      3.922308,
      3.926128,
      3.955113,
      3.959875,
      4.153963,
      4.164011,
      3.713678,
      3.69052,
      4.177348,
      4.177196,
      3.722122,
      3.688723,
      3.710523,
      3.684007,
      4.170391,
      4.174159,
      3.716252,
      3.708303,
      3.91198,
      3.904558,
      3.964131,
      3.955901,
      4.130878,
      4.136131,
      3.934052,
      3.940361,
      3.961265,
      3.96775,
      4.143864,
      4.153646,
      4.018155,
      4.021917,
      3.972997,
      3.993894,
      4.029631,
      4.035687,
      4.049685,
      4.052662,
      4.101553,
      4.089303,
      4.001209,
      4.010592,
      3.959942,
      3.959915,
      4.00934,
      4.017858,
      4.013872,
      4.012608,
      3.995703,
      3.980381,
      4.017044,
      4.020733,
      4.051029,
      4.043262,
      4.091986,
      4.074447,
      3.998663,
      3.997214,
      3.956438,
      3.947254,
      4.011218,
      4.027799,
      4.005444,
      4.007906,
      3.984175,
      3.975555,
      4.037471,
      4.026644,
      4.058555,
      4.063722,
      4.086265,
      4.095047,
      4.011039,
      4.005292,
      3.961091,
      3.964379,
      4.024413,
      4.024035,
      3.931052,
      3.932868,
      3.963371,
      3.959977,
      4.138598,
      4.127582,
      3.55525,
      3.570867,
      3.387374,
      3.365836,
      3.643646,
      3.621319,
      3.408467,
      3.393552,
      3.53308,
      3.548246,
      3.428507,
      3.432271,
      3.557173,
      3.553825,
      3.379897,
      3.385491,
      3.612598,
      3.624273,
      3.413506,
      3.436546,
      3.544187,
      3.538623,
      3.35036,
      3.340389,
      2.517697,
      2.558609,
      2.549217,
      2.532708,
      2.555799,
      2.534167,
      2.550791,
      2.520742,
      2.536735,
      2.544303,
      2.532805,
      2.551372
    ],
    "lowdin_charges":[
      0.133623,
      0.134525,
      0.13595,
      0.13163,
      0.113922,
      0.112246,
      0.112014,
      0.115565,
      0.138569,
      0.135697,
      0.13282,
      0.110588,
      0.11904,
      0.122173,
      0.135242,
      0.132995,
      0.106156,
      0.091478,
      0.109712,
      0.11135,
      0.12436,
      0.126544,
      0.0905,
      0.107337,
      0.093924,
      0.11067,
      0.138023,
      0.140072,
      0.124997,
      0.130368,
      0.124314,
      0.125443,
      0.106548,
      0.11277,
      0.099022,
      0.078226,
      0.138198,
      0.138634,
      0.128462,
      0.133985,
      0.12228,
      0.123853,
      0.127186,
      0.107937,
      0.076498,
      0.093453,
      0.13417,
      0.134955,
      0.129536,
      0.131869,
      0.137161,
      0.136361,
      0.103916,
      0.111615,
      0.113392,
      0.114506,
      0.094155,
      0.089885,
      0.094051,
      0.090586,
      0.138114,
      0.136917,
      0.113157,
      0.127203,
      0.117926,
      0.121627,
      0.132867,
      0.137106,
      0.089449,
      0.112295,
      0.112809,
      0.117613,
      0.126167,
      0.123076,
      0.127248,
      0.120159,
      0.088273,
      0.090539,
      0.136992,
      0.133529,
      0.132729,
      0.134414,
      0.126918,
      0.124704,
      0.096386,
      0.104296,
      0.079752,
      0.121952,
      0.139449,
      0.139479,
      0.132203,
      0.131734,
      0.119929,
      0.127346,
      0.096486,
      0.119234,
      0.101221,
      0.098072,
      0.133894,
      0.140913,
      0.127021,
      0.131506,
      0.135789,
      0.135529,
      0.133931,
      0.115472,
      0.123714,
      0.120595,
      -0.09826,
      -0.098574,
      -0.086075,
      -0.086751,
      -0.109015,
      -0.102059,
      -0.100661,
      -0.100736,
      -0.083374,
      -0.080709,
      -0.109163,
      -0.112357,
      -0.019362,
      -0.024896,
      -0.179464,
      -0.17301,
      -0.016545,
      -0.019196,
      -0.027187,
      -0.019802,
      -0.174966,
      -0.181038,
      -0.020909,
      -0.016489,
      -0.101225,
      -0.108754,
      -0.160532,
      -0.153649,
      -0.220672,
      -0.211536,
      -0.128701,
      -0.117107,
      -0.146606,
      -0.147161,
      -0.225733,
      -0.228167,
      -0.073577,
      -0.076582,
      -0.074038,
      -0.089739,
      -0.09022,
      -0.092923,
      -0.068621,
      -0.071947,
      -0.10029,
      -0.103343,
      -0.094004,
      -0.092863,
      -0.062555,
      -0.061773,
      -0.089209,
      -0.088676,
      -0.079265,
      -0.074481,
      -0.090214,
      -0.086055,
      -0.098537,
      -0.08966,
      -0.082163,
      -0.083168,
      -0.112039,
      -0.112131,
      -0.089928,
      -0.094931,
      -0.060429,
      -0.063523,
      -0.081476,
      -0.076347,
      -0.073025,
      -0.072651,
      -0.095308,
      -0.085738,
      -0.092387,
      -0.098706,
      -0.079196,
      -0.072705,
      -0.112494,
      -0.110216,
      -0.097828,
      -0.094264,
      -0.066617,
      -0.066067,
      -0.074661,
      -0.076065,
      -0.101,
      -0.107832,
      -0.147346,
      -0.148907,
      -0.225312,
      -0.226671,
      -0.071949,
      -0.067253,
      -0.12899,
      -0.128655,
      -0.061457,
      -0.042413,
      -0.072576,
      -0.070253,
      -0.125011,
      -0.129605,
      -0.050253,
      -0.060572,
      -0.103155,
      -0.095979,
      -0.154411,
      -0.169738,
      -0.215417,
      -0.221019,
      -0.115619,
      -0.129297,
      -0.147884,
      -0.153371,
      -0.231198,
      -0.228394,
      -0.072953,
      -0.075303,
      -0.099463,
      -0.088156,
      -0.094069,
      -0.09528,
      -0.076868,
      -0.083825,
      -0.115473,
      -0.112211,
      -0.095562,
      -0.097025,
      -0.064025,
      -0.064393,
      -0.074861,
      -0.073758,
      -0.077618,
      -0.085904,
      -0.082192,
      -0.086405,
      -0.082531,
      -0.097404,
      -0.071624,
      -0.069061,
      -0.106544,
      -0.103033,
      -0.094483,
      -0.08681,
      -0.064235,
      -0.058604,
      -0.078336,
      -0.087431,
      -0.071391,
      -0.075359,
      -0.084373,
      -0.081923,
      -0.097659,
      -0.101958,
      -0.081096,
      -0.085623,
      -0.105348,
      -0.110897,
      -0.092887,
      -0.097908,
      -0.062764,
      -0.064975,
      -0.085108,
      -0.083321,
      -0.118046,
      -0.115319,
      -0.151274,
      -0.15001,
      -0.217751,
      -0.210472,
      0.115749,
      0.117375,
      0.128424,
      0.12207,
      0.127998,
      0.123768,
      0.117694,
      0.115451,
      0.1271,
      0.1382,
      0.122763,
      0.12084,
      0.11309,
      0.117759,
      0.125979,
      0.133042,
      0.12042,
      0.122143,
      0.118272,
      0.122923,
      0.129364,
      0.127495,
      0.117587,
      0.115118,
      0.09216,
      0.104758,
      0.107414,
      0.103193,
      0.104465,
      0.102057,
      0.106239,
      0.093493,
      0.098503,
      0.095022,
      0.099932,
      0.104867
    ],
    "hirshfeld_charges":[
      0.453,
      0.454,
      0.454,
      0.453,
      0.476,
      0.475,
      0.474,
      0.477,
      0.461,
      0.461,
      0.527,
      0.524,
      0.44,
      0.441,
      0.463,
      0.463,
      0.526,
      0.528,
      0.436,
      0.438,
      0.449,
      0.448,
      0.459,
      0.459,
      0.454,
      0.454,
      0.454,
      0.456,
      0.459,
      0.459,
      0.448,
      0.448,
      0.457,
      0.459,
      0.452,
      0.453,
      0.457,
      0.456,
      0.46,
      0.458,
      0.449,
      0.449,
      0.46,
      0.457,
      0.452,
      0.453,
      0.455,
      0.455,
      0.458,
      0.458,
      0.461,
      0.461,
      0.526,
      0.527,
      0.439,
      0.439,
      0.441,
      0.442,
      0.44,
      0.442,
      0.461,
      0.462,
      0.525,
      0.527,
      0.44,
      0.442,
      0.463,
      0.463,
      0.528,
      0.526,
      0.439,
      0.438,
      0.448,
      0.449,
      0.459,
      0.46,
      0.453,
      0.455,
      0.456,
      0.455,
      0.459,
      0.458,
      0.448,
      0.447,
      0.458,
      0.458,
      0.454,
      0.454,
      0.455,
      0.456,
      0.458,
      0.459,
      0.449,
      0.448,
      0.459,
      0.46,
      0.453,
      0.454,
      0.455,
      0.455,
      0.459,
      0.459,
      0.462,
      0.461,
      0.527,
      0.526,
      0.441,
      0.441,
      -0.455,
      -0.449,
      -0.024,
      -0.025,
      0.078,
      0.088,
      -0.455,
      -0.459,
      -0.017,
      -0.017,
      0.08,
      0.074,
      -0.457,
      -0.467,
      -0.019,
      -0.011,
      0.079,
      0.075,
      -0.47,
      -0.458,
      -0.011,
      -0.019,
      0.071,
      0.078,
      -0.463,
      -0.467,
      -0.285,
      -0.268,
      0.199,
      0.2,
      -0.503,
      -0.48,
      -0.271,
      -0.272,
      0.186,
      0.186,
      -0.43,
      -0.438,
      -0.434,
      -0.466,
      -0.44,
      -0.464,
      0.226,
      0.229,
      -0.001,
      -0.006,
      -0.424,
      -0.415,
      -0.39,
      -0.386,
      0.197,
      0.201,
      -0.435,
      -0.435,
      -0.481,
      -0.455,
      -0.456,
      -0.437,
      0.21,
      0.214,
      -0.014,
      -0.007,
      -0.421,
      -0.427,
      -0.382,
      -0.394,
      0.217,
      0.216,
      -0.434,
      -0.431,
      -0.463,
      -0.478,
      -0.441,
      -0.44,
      0.22,
      0.225,
      -0.013,
      -0.017,
      -0.426,
      -0.426,
      -0.389,
      -0.39,
      0.209,
      0.214,
      -0.46,
      -0.475,
      -0.274,
      -0.273,
      0.188,
      0.191,
      -0.475,
      -0.468,
      -0.014,
      -0.007,
      0.051,
      0.067,
      -0.474,
      -0.475,
      -0.003,
      -0.011,
      0.063,
      0.049,
      -0.46,
      -0.453,
      -0.272,
      -0.296,
      0.197,
      0.197,
      -0.478,
      -0.506,
      -0.272,
      -0.281,
      0.185,
      0.186,
      -0.432,
      -0.425,
      -0.477,
      -0.467,
      -0.447,
      -0.43,
      0.217,
      0.211,
      -0.017,
      -0.014,
      -0.423,
      -0.431,
      -0.388,
      -0.393,
      0.219,
      0.215,
      -0.437,
      -0.446,
      -0.432,
      -0.462,
      -0.44,
      -0.459,
      0.228,
      0.23,
      -0.0,
      -0.003,
      -0.42,
      -0.418,
      -0.396,
      -0.386,
      0.213,
      0.205,
      -0.426,
      -0.442,
      -0.453,
      -0.453,
      -0.442,
      -0.465,
      0.216,
      0.212,
      -0.009,
      -0.009,
      -0.425,
      -0.424,
      -0.386,
      -0.386,
      0.203,
      0.206,
      -0.487,
      -0.481,
      -0.266,
      -0.261,
      0.192,
      0.195,
      -0.608,
      -0.611,
      -0.361,
      -0.362,
      -0.609,
      -0.616,
      -0.378,
      -0.376,
      -0.644,
      -0.625,
      -0.371,
      -0.38,
      -0.618,
      -0.604,
      -0.358,
      -0.352,
      -0.618,
      -0.61,
      -0.377,
      -0.378,
      -0.629,
      -0.635,
      -0.365,
      -0.36,
      -0.452,
      -0.453,
      -0.444,
      -0.448,
      -0.457,
      -0.449,
      -0.455,
      -0.461,
      -0.456,
      -0.456,
      -0.448,
      -0.45
    ],
    "mulliken_charges":[
      0.066845,
      0.070241,
      0.070583,
      0.066892,
      0.074079,
      0.069981,
      0.069547,
      0.074735,
      0.067322,
      0.066093,
      0.133765,
      0.123211,
      0.06906,
      0.072141,
      0.068618,
      0.065653,
      0.122307,
      0.125077,
      0.061166,
      0.064659,
      0.068979,
      0.067549,
      0.06017,
      0.06585,
      0.063893,
      0.066034,
      0.072428,
      0.077112,
      0.078675,
      0.081571,
      0.066277,
      0.067229,
      0.066202,
      0.068673,
      0.059165,
      0.056115,
      0.075487,
      0.074013,
      0.081025,
      0.079271,
      0.066183,
      0.069228,
      0.075517,
      0.065386,
      0.053024,
      0.061541,
      0.074025,
      0.072883,
      0.081391,
      0.081166,
      0.067049,
      0.069141,
      0.124796,
      0.122938,
      0.064121,
      0.06428,
      0.056279,
      0.056912,
      0.057043,
      0.056674,
      0.066694,
      0.068413,
      0.125506,
      0.131354,
      0.070077,
      0.072576,
      0.06547,
      0.069291,
      0.124271,
      0.126276,
      0.064974,
      0.064883,
      0.067273,
      0.069504,
      0.07289,
      0.072622,
      0.055409,
      0.061259,
      0.076152,
      0.071578,
      0.081952,
      0.078843,
      0.067486,
      0.06617,
      0.061432,
      0.065267,
      0.058978,
      0.069173,
      0.073213,
      0.074853,
      0.078806,
      0.081371,
      0.067376,
      0.066612,
      0.064367,
      0.070462,
      0.062716,
      0.063699,
      0.071822,
      0.07608,
      0.080413,
      0.08182,
      0.067934,
      0.065274,
      0.133424,
      0.130236,
      0.074296,
      0.072829,
      -0.084999,
      -0.087284,
      -0.025629,
      -0.024685,
      0.029956,
      0.036837,
      -0.089337,
      -0.087227,
      -0.022874,
      -0.022383,
      0.034093,
      0.030807,
      -0.050115,
      -0.055565,
      -0.044473,
      -0.037778,
      0.026346,
      0.025447,
      -0.058241,
      -0.050704,
      -0.038426,
      -0.04532,
      0.023698,
      0.026085,
      -0.062537,
      -0.068993,
      0.013863,
      0.032139,
      0.038239,
      0.046323,
      -0.10217,
      -0.075311,
      0.035024,
      0.033749,
      0.035687,
      0.031893,
      -0.029972,
      -0.03241,
      -0.06819,
      -0.087653,
      -0.062939,
      -0.063961,
      0.122303,
      0.11739,
      -0.038994,
      -0.041647,
      -0.044786,
      -0.0433,
      -0.012826,
      -0.011949,
      0.094138,
      0.094648,
      -0.034755,
      -0.032732,
      -0.094449,
      -0.076524,
      -0.066655,
      -0.06338,
      0.105868,
      0.107394,
      -0.048039,
      -0.045749,
      -0.044413,
      -0.050174,
      -0.010574,
      -0.012591,
      0.104804,
      0.108114,
      -0.028385,
      -0.029908,
      -0.083677,
      -0.083287,
      -0.066259,
      -0.066979,
      0.109146,
      0.117102,
      -0.049075,
      -0.050783,
      -0.056074,
      -0.046573,
      -0.017433,
      -0.015799,
      0.107869,
      0.104297,
      -0.06478,
      -0.082448,
      0.034464,
      0.033332,
      0.034371,
      0.029862,
      -0.064539,
      -0.062663,
      -0.036401,
      -0.02872,
      0.019225,
      0.03533,
      -0.066591,
      -0.064425,
      -0.027572,
      -0.035068,
      0.032671,
      0.017874,
      -0.062831,
      -0.05683,
      0.029654,
      0.004757,
      0.043858,
      0.036996,
      -0.074388,
      -0.102625,
      0.032557,
      0.028495,
      0.03138,
      0.035337,
      -0.026742,
      -0.029675,
      -0.09081,
      -0.078135,
      -0.064539,
      -0.061739,
      0.109686,
      0.106495,
      -0.051325,
      -0.048116,
      -0.051224,
      -0.051686,
      -0.015522,
      -0.01462,
      0.108926,
      0.109076,
      -0.032793,
      -0.041935,
      -0.069473,
      -0.083652,
      -0.05897,
      -0.06144,
      0.116269,
      0.120762,
      -0.04052,
      -0.040774,
      -0.043792,
      -0.035316,
      -0.014712,
      -0.008447,
      0.104871,
      0.097852,
      -0.028419,
      -0.032082,
      -0.083271,
      -0.071856,
      -0.063241,
      -0.078167,
      0.109092,
      0.105016,
      -0.043922,
      -0.046885,
      -0.04511,
      -0.053392,
      -0.013135,
      -0.012693,
      0.097969,
      0.101205,
      -0.089283,
      -0.077898,
      0.033628,
      0.037434,
      0.034484,
      0.044575,
      -0.099344,
      -0.104527,
      -0.210544,
      -0.222931,
      -0.055446,
      -0.075647,
      -0.232109,
      -0.233241,
      -0.096606,
      -0.068783,
      -0.228026,
      -0.227154,
      -0.111801,
      -0.095931,
      -0.22012,
      -0.206039,
      -0.081188,
      -0.061882,
      -0.232583,
      -0.227116,
      -0.084192,
      -0.098299,
      -0.220592,
      -0.227614,
      -0.2227,
      -0.21263,
      -0.206449,
      -0.214134,
      -0.215128,
      -0.216078,
      -0.214119,
      -0.226982,
      -0.221973,
      -0.222198,
      -0.214962,
      -0.210206
    ],
    "band_gap_PBE0":1.366975,
    "fermi_level_PBE0":-2.765204,
    "energy_PBE0":-1449.3233577981218,
    "eqeq_charges":[
      0.028,
      0.028,
      0.028,
      0.028,
      0.028,
      0.028,
      0.028,
      0.028,
      0.028,
      0.028,
      0.028,
      0.028,
      0.028,
      0.028,
      0.028,
      0.028,
      0.028,
      0.028,
      0.028,
      0.028,
      0.028,
      0.028,
      0.028,
      0.028,
      0.028,
      0.028,
      0.028,
      0.028,
      0.028,
      0.028,
      0.028,
      0.028,
      0.028,
      0.028,
      0.028,
      0.028,
      0.028,
      0.028,
      0.028,
      0.028,
      0.028,
      0.028,
      0.028,
      0.028,
      0.028,
      0.028,
      0.028,
      0.028,
      0.028,
      0.028,
      0.028,
      0.028,
      0.028,
      0.028,
      0.028,
      0.028,
      0.028,
      0.028,
      0.028,
      0.028,
      0.028,
      0.028,
      0.028,
      0.028,
      0.028,
      0.028,
      0.028,
      0.028,
      0.028,
      0.028,
      0.028,
      0.028,
      0.028,
      0.028,
      0.028,
      0.028,
      0.028,
      0.028,
      0.028,
      0.028,
      0.028,
      0.028,
      0.028,
      0.028,
      0.029,
      0.029,
      0.029,
      0.029,
      0.029,
      0.029,
      0.029,
      0.029,
      0.029,
      0.029,
      0.029,
      0.029,
      0.029,
      0.029,
      0.029,
      0.029,
      0.029,
      0.029,
      0.029,
      0.029,
      0.029,
      0.029,
      0.029,
      0.029,
      -0.001,
      -0.001,
      -0.001,
      -0.001,
      -0.001,
      -0.001,
      -0.001,
      -0.001,
      -0.001,
      -0.001,
      -0.001,
      -0.001,
      -0.001,
      -0.001,
      -0.001,
      -0.001,
      -0.001,
      -0.001,
      -0.001,
      -0.001,
      -0.001,
      -0.001,
      -0.001,
      -0.001,
      -0.001,
      -0.001,
      -0.001,
      -0.001,
      -0.001,
      -0.001,
      -0.001,
      -0.001,
      -0.001,
      -0.001,
      -0.001,
      -0.001,
      -0.001,
      -0.001,
      -0.001,
      -0.001,
      -0.001,
      -0.001,
      -0.001,
      -0.001,
      -0.001,
      -0.001,
      -0.001,
      -0.001,
      -0.001,
      -0.001,
      -0.001,
      -0.001,
      -0.001,
      -0.001,
      -0.001,
      -0.001,
      -0.001,
      -0.001,
      -0.001,
      -0.001,
      -0.001,
      -0.001,
      -0.001,
      -0.001,
      -0.001,
      -0.001,
      -0.001,
      -0.001,
      -0.001,
      -0.001,
      -0.001,
      -0.001,
      -0.001,
      -0.001,
      -0.001,
      -0.001,
      -0.001,
      -0.001,
      -0.001,
      -0.001,
      -0.001,
      -0.001,
      -0.001,
      -0.001,
      -0.001,
      -0.001,
      -0.001,
      -0.001,
      -0.001,
      -0.001,
      -0.001,
      -0.001,
      -0.001,
      -0.001,
      -0.001,
      -0.001,
      -0.001,
      -0.001,
      -0.001,
      -0.001,
      -0.001,
      -0.001,
      -0.001,
      -0.001,
      -0.001,
      -0.001,
      -0.001,
      -0.001,
      -0.001,
      -0.001,
      -0.001,
      -0.001,
      -0.001,
      -0.001,
      -0.001,
      -0.001,
      -0.001,
      -0.001,
      -0.001,
      -0.001,
      -0.001,
      -0.001,
      -0.001,
      -0.001,
      -0.001,
      -0.001,
      -0.001,
      -0.001,
      -0.001,
      -0.001,
      -0.001,
      -0.001,
      -0.001,
      -0.001,
      -0.001,
      -0.001,
      -0.001,
      -0.001,
      -0.001,
      -0.001,
      -0.001,
      -0.001,
      -0.001,
      -0.001,
      -0.001,
      -0.001,
      -0.001,
      -0.001,
      -0.001,
      -0.001,
      -0.001,
      -0.001,
      -0.001,
      -0.001,
      -0.001,
      -0.001,
      -0.001,
      -0.001,
      -0.001,
      -0.001,
      -0.001,
      -0.001,
      -0.001,
      -0.001,
      -0.001,
      -0.001,
      -0.001,
      -0.001,
      -0.067,
      -0.067,
      -0.067,
      -0.067,
      -0.067,
      -0.067,
      -0.067,
      -0.067,
      -0.067,
      -0.067,
      -0.067,
      -0.067,
      -0.067,
      -0.067,
      -0.067,
      -0.067,
      -0.067,
      -0.067,
      -0.067,
      -0.067,
      -0.067,
      -0.067,
      -0.067,
      -0.067,
      -0.106,
      -0.106,
      -0.106,
      -0.106,
      -0.106,
      -0.106,
      -0.106,
      -0.106,
      -0.106,
      -0.106,
      -0.106,
      -0.106
    ]
  },
  "optimization":{
    "description":"Information about the optimization process such as level of calculations, optimization schema and optimization steps.",
    "opt1":{
      "energy":[
        -1449.7719162669,
        -1450.0948200998,
        -1450.2463536399,
        -1450.3394967332,
        -1450.3965316075,
        -1450.4685395829,
        -1450.4991637207,
        -1450.5341146586,
        -1450.5568889657,
        -1450.5796263025,
        -1450.6029622718,
        -1450.6311913994,
        -1450.6424815913,
        -1450.6602583753,
        -1450.6722140795,
        -1450.687808824,
        -1450.6970283116,
        -1450.7083852849,
        -1450.7277277376,
        -1450.7378345568
      ]
    },
    "bomd":{
      "energy":[
        -1450.7378345637,
        -1450.7270972779,
        -1450.6955059817,
        -1450.6516087779,
        -1450.6039516764,
        -1450.5602467897,
        -1450.5237813849,
        -1450.4963086995,
        -1450.4719312933,
        -1450.4473384809,
        -1450.4161052148,
        -1450.376789506,
        -1450.3247813272,
        -1450.2646179579,
        -1450.2066484293,
        -1450.1610113298,
        -1450.1378328459,
        -1450.1422816364,
        -1450.1677803932,
        -1450.2023730905,
        -1450.2324603097,
        -1450.2488269659,
        -1450.2500639813,
        -1450.2378196325,
        -1450.2182369498,
        -1450.1985884558,
        -1450.1859712361,
        -1450.1848869625,
        -1450.1959347549,
        -1450.2151687418,
        -1450.2366076425,
        -1450.2531494301,
        -1450.2590703658,
        -1450.2520912871,
        -1450.2345480657,
        -1450.2115447172,
        -1450.1891914943,
        -1450.178253075,
        -1450.1829975982,
        -1450.2021589326,
        -1450.2299907851,
        -1450.2573495567,
        -1450.2793741862,
        -1450.2894755161,
        -1450.2865610803,
        -1450.274786285,
        -1450.2578607204,
        -1450.2406100296,
        -1450.2306388424,
        -1450.2304300084,
        -1450.2392551076,
        -1450.2534163943,
        -1450.2670898038,
        -1450.274024134,
        -1450.2684145154,
        -1450.250216648,
        -1450.2203304124,
        -1450.1859056717,
        -1450.1554175832,
        -1450.1389887172,
        -1450.137290552,
        -1450.1469655363,
        -1450.1601811826,
        -1450.1681198001,
        -1450.1658913044,
        -1450.1522880711,
        -1450.1301929882,
        -1450.1045521414,
        -1450.0821438293,
        -1450.070520521,
        -1450.0733918181,
        -1450.090233849,
        -1450.1160133752,
        -1450.1429794047,
        -1450.1665055667,
        -1450.1823833182,
        -1450.189009112,
        -1450.1889139902,
        -1450.187115478,
        -1450.1898676459,
        -1450.2014805058,
        -1450.2234734211,
        -1450.2527703269,
        -1450.2820177248,
        -1450.305019468,
        -1450.3172508716,
        -1450.319508605,
        -1450.3142899696,
        -1450.3044377299,
        -1450.2946881285,
        -1450.2893406596,
        -1450.2892339048,
        -1450.2929221802,
        -1450.2975551085,
        -1450.2990790238,
        -1450.2956223197,
        -1450.2861780414,
        -1450.2713256597,
        -1450.2539460731,
        -1450.2374178742,
        -1450.2265604751
      ]
    },
    "opt2":{
      "energy":[
        -1450.1799777497,
        -1450.2522923606,
        -1450.3343186541,
        -1450.3655040324,
        -1450.4009099912,
        -1450.4164235594,
        -1450.4336756623,
        -1450.4482068856,
        -1450.4617971431,
        -1450.4676137861,
        -1450.4767897073,
        -1450.4820912058,
        -1450.4883679227,
        -1450.4926052443,
        -1450.4959688301,
        -1450.499238539,
        -1450.5028009367,
        -1450.5052222792,
        -1450.5086735545,
        -1450.5100475284,
        -1450.5137477269,
        -1450.5154340703,
        -1450.5172661325,
        -1450.5198348362,
        -1450.5220210763,
        -1450.5236555789,
        -1450.5255030858,
        -1450.5269075008,
        -1450.5287451511,
        -1450.5303807226,
        -1450.5320204613,
        -1450.5333511288,
        -1450.5346912702,
        -1450.5359584249,
        -1450.5371585606,
        -1450.538588823,
        -1450.540326545,
        -1450.541609983,
        -1450.5429918062,
        -1450.5445268105,
        -1450.5460088506,
        -1450.5477158993,
        -1450.5497294545,
        -1450.5509516033,
        -1450.5531549605,
        -1450.5552150993,
        -1450.5583005778,
        -1450.5604094404,
        -1450.5631519412,
        -1450.5652097629,
        -1450.5675941994,
        -1450.5707290028,
        -1450.5735522541,
        -1450.5776058759,
        -1450.5802425552,
        -1450.584348577,
        -1450.5896089273,
        -1450.5935974786,
        -1450.5977735343,
        -1450.6038025602,
        -1450.6090813262,
        -1450.6119473834,
        -1450.6175706,
        -1450.6212557093,
        -1450.625216324,
        -1450.6292486127,
        -1450.6329041563,
        -1450.6358665136,
        -1450.6399227342,
        -1450.642095146,
        -1450.6455164838,
        -1450.6476427432,
        -1450.6499493602,
        -1450.653504429,
        -1450.6558792616,
        -1450.6581831666,
        -1450.6601830509,
        -1450.6620812603,
        -1450.6630596336,
        -1450.6658369334,
        -1450.6668142145,
        -1450.6682378256,
        -1450.6693202261,
        -1450.6711390129,
        -1450.6722380965,
        -1450.6732628749,
        -1450.6749359659,
        -1450.6758482934,
        -1450.6771382352,
        -1450.6780495412,
        -1450.6798484654,
        -1450.6818067867,
        -1450.6832304429,
        -1450.684544678,
        -1450.6856777889,
        -1450.6870111938,
        -1450.68778528,
        -1450.6891845276,
        -1450.690290029,
        -1450.69102649,
        -1450.6920981431,
        -1450.6935599536,
        -1450.6945241178,
        -1450.69590833,
        -1450.6970887777,
        -1450.6979121419,
        -1450.6985677152,
        -1450.6993497856,
        -1450.6998478621,
        -1450.7007722679,
        -1450.7016237036,
        -1450.7023384563,
        -1450.7030083493,
        -1450.7037515087,
        -1450.7046045514,
        -1450.7054376251,
        -1450.7059979748,
        -1450.706605282,
        -1450.7073323482,
        -1450.7082039148,
        -1450.7087365131,
        -1450.7093793809,
        -1450.709977771,
        -1450.7106972949,
        -1450.7111190317,
        -1450.7119934997,
        -1450.7125202957,
        -1450.713095464,
        -1450.7136473606,
        -1450.7143314356,
        -1450.7147467793,
        -1450.7151457615,
        -1450.7156626406,
        -1450.7163822769,
        -1450.7170420152,
        -1450.7172647578,
        -1450.7179107956,
        -1450.7184795317,
        -1450.7188643625,
        -1450.7194015303,
        -1450.719562126,
        -1450.7197272643,
        -1450.720014979,
        -1450.7202345025,
        -1450.720536439,
        -1450.7208669676,
        -1450.7212145248,
        -1450.7215125505,
        -1450.7218308267,
        -1450.7221705694,
        -1450.7223630609,
        -1450.7225921912,
        -1450.7230145954,
        -1450.7232988105,
        -1450.7234945774,
        -1450.7238027915,
        -1450.7240998684,
        -1450.7243319277,
        -1450.7246327943,
        -1450.7252007583,
        -1450.7253130936,
        -1450.7257536579,
        -1450.7260662926,
        -1450.7263840674,
        -1450.7268358487,
        -1450.7270571695,
        -1450.7274972635,
        -1450.7277214413,
        -1450.7279727259,
        -1450.7281802985,
        -1450.7284713485,
        -1450.7286904485,
        -1450.7288415384,
        -1450.7291370477,
        -1450.7296139577,
        -1450.7298402599,
        -1450.7302219301,
        -1450.7304948572,
        -1450.7306498061,
        -1450.730835605,
        -1450.7311743358,
        -1450.7313988912,
        -1450.7316096027,
        -1450.7318893928,
        -1450.7322425033,
        -1450.7326027089,
        -1450.7329979935,
        -1450.7332812958,
        -1450.7335858869,
        -1450.7338240659,
        -1450.7340286505,
        -1450.7342402303,
        -1450.7344295164,
        -1450.7347050451,
        -1450.734919282,
        -1450.735131115,
        -1450.7353618932,
        -1450.7355903582,
        -1450.735860703,
        -1450.7361235708,
        -1450.736307006,
        -1450.7365944453,
        -1450.7367239154,
        -1450.7369548605,
        -1450.737074975,
        -1450.7374441601,
        -1450.7375910606,
        -1450.7378133561,
        -1450.7380774879,
        -1450.738342125,
        -1450.7385843583,
        -1450.7387400116,
        -1450.7389995417,
        -1450.7392638259,
        -1450.7393849278,
        -1450.7396480098,
        -1450.7397324391,
        -1450.7399136403,
        -1450.740099388,
        -1450.7402633762,
        -1450.7405121814,
        -1450.7408970762,
        -1450.7411083999,
        -1450.741231943,
        -1450.7415075933,
        -1450.7416969353,
        -1450.7420419927,
        -1450.7423269815,
        -1450.7426687819,
        -1450.7428763378,
        -1450.7431693967,
        -1450.7435244653,
        -1450.7439675649,
        -1450.7443636705,
        -1450.7446635416,
        -1450.7451585787,
        -1450.7455060296,
        -1450.7458810082,
        -1450.7460584009,
        -1450.7462529072,
        -1450.7465478046,
        -1450.746708044,
        -1450.7469231486,
        -1450.7471676355,
        -1450.7474119039,
        -1450.7477689311,
        -1450.7477871089,
        -1450.7482340116,
        -1450.748374899,
        -1450.7485591332,
        -1450.7488089157,
        -1450.7489661139,
        -1450.7492283223,
        -1450.749334219,
        -1450.7495738959,
        -1450.7497378887,
        -1450.74987914,
        -1450.7500143013,
        -1450.7500943702,
        -1450.7502438316,
        -1450.7503624752,
        -1450.7504730595,
        -1450.7506307159,
        -1450.750760229,
        -1450.7509042894,
        -1450.7510133383,
        -1450.751013338
      ]
    }
  },
  "adsorption":{
    "description":"Information about the adsorption simulation experiments on RASPA2"
  },
  "textural":{
    "description":"Information about the textural calculations of the structure such as specific area, pore volume, void fraction.",
    "number_of_channels":1,
    "channel_dimentionality":1,
    "channel_size":[
      38.2786,
      37.7351,
      38.2786
    ],
    "density":0.313806,
    "acessible_volume_fraction":0.688,
    "pore_volume_cm3/g":2.19244,
    "specific_area":{
      "A2":1230.36,
      "m2/cm3":875.794,
      "m2/g":2790.88
    },
    "psd":{
      "bins":[
        0.0,
        0.1,
        0.2,
        0.3,
        0.4,
        0.5,
        0.6,
        0.7,
        0.8,
        0.9,
        1.0,
        1.1,
        1.2,
        1.3,
        1.4,
        1.5,
        1.6,
        1.7,
        1.8,
        1.9,
        2.0,
        2.1,
        2.2,
        2.3,
        2.4,
        2.5,
        2.6,
        2.7,
        2.8,
        2.9,
        3.0,
        3.1,
        3.2,
        3.3,
        3.4,
        3.5,
        3.6,
        3.7,
        3.8,
        3.9,
        4.0,
        4.1,
        4.2,
        4.3,
        4.4,
        4.5,
        4.6,
        4.7,
        4.8,
        4.9,
        5.0,
        5.1,
        5.2,
        5.3,
        5.4,
        5.5,
        5.6,
        5.7,
        5.8,
        5.9,
        6.0,
        6.1,
        6.2,
        6.3,
        6.4,
        6.5,
        6.6,
        6.7,
        6.8,
        6.9,
        7.0,
        7.1,
        7.2,
        7.3,
        7.4,
        7.5,
        7.6,
        7.7,
        7.8,
        7.9,
        8.0,
        8.1,
        8.2,
        8.3,
        8.4,
        8.5,
        8.6,
        8.7,
        8.8,
        8.9,
        9.0,
        9.1,
        9.2,
        9.3,
        9.4,
        9.5,
        9.6,
        9.7,
        9.8,
        9.9,
        10.0,
        10.1,
        10.2,
        10.3,
        10.4,
        10.5,
        10.6,
        10.7,
        10.8,
        10.9,
        11.0,
        11.1,
        11.2,
        11.3,
        11.4,
        11.5,
        11.6,
        11.7,
        11.8,
        11.9,
        12.0,
        12.1,
        12.2,
        12.3,
        12.4,
        12.5,
        12.6,
        12.7,
        12.8,
        12.9,
        13.0,
        13.1,
        13.2,
        13.3,
        13.4,
        13.5,
        13.6,
        13.7,
        13.8,
        13.9,
        14.0,
        14.1,
        14.2,
        14.3,
        14.4,
        14.5,
        14.6,
        14.7,
        14.8,
        14.9,
        15.0,
        15.1,
        15.2,
        15.3,
        15.4,
        15.5,
        15.6,
        15.7,
        15.8,
        15.9,
        16.0,
        16.1,
        16.2,
        16.3,
        16.4,
        16.5,
        16.6,
        16.7,
        16.8,
        16.9,
        17.0,
        17.1,
        17.2,
        17.3,
        17.4,
        17.5,
        17.6,
        17.7,
        17.8,
        17.9,
        18.0,
        18.1,
        18.2,
        18.3,
        18.4,
        18.5,
        18.6,
        18.7,
        18.8,
        18.9,
        19.0,
        19.1,
        19.2,
        19.3,
        19.4,
        19.5,
        19.6,
        19.7,
        19.8,
        19.9,
        20.0,
        20.1,
        20.2,
        20.3,
        20.4,
        20.5,
        20.6,
        20.7,
        20.8,
        20.9,
        21.0,
        21.1,
        21.2,
        21.3,
        21.4,
        21.5,
        21.6,
        21.7,
        21.8,
        21.9,
        22.0,
        22.1,
        22.2,
        22.3,
        22.4,
        22.5,
        22.6,
        22.7,
        22.8,
        22.9,
        23.0,
        23.1,
        23.2,
        23.3,
        23.4,
        23.5,
        23.6,
        23.7,
        23.8,
        23.9,
        24.0,
        24.1,
        24.2,
        24.3,
        24.4,
        24.5,
        24.6,
        24.7,
        24.8,
        24.9,
        25.0,
        25.1,
        25.2,
        25.3,
        25.4,
        25.5,
        25.6,
        25.7,
        25.8,
        25.9,
        26.0,
        26.1,
        26.2,
        26.3,
        26.4,
        26.5,
        26.6,
        26.7,
        26.8,
        26.9,
        27.0,
        27.1,
        27.2,
        27.3,
        27.4,
        27.5,
        27.6,
        27.7,
        27.8,
        27.9,
        28.0,
        28.1,
        28.2,
        28.3,
        28.4,
        28.5,
        28.6,
        28.7,
        28.8,
        28.9,
        29.0,
        29.1,
        29.2,
        29.3,
        29.4,
        29.5,
        29.6,
        29.7,
        29.8,
        29.9,
        30.0,
        30.1,
        30.2,
        30.3,
        30.4,
        30.5,
        30.6,
        30.7,
        30.8,
        30.9,
        31.0,
        31.1,
        31.2,
        31.3,
        31.4,
        31.5,
        31.6,
        31.7,
        31.8,
        31.9,
        32.0,
        32.1,
        32.2,
        32.3,
        32.4,
        32.5,
        32.6,
        32.7,
        32.8,
        32.9,
        33.0,
        33.1,
        33.2,
        33.3,
        33.4,
        33.5,
        33.6,
        33.7,
        33.8,
        33.9,
        34.0,
        34.1,
        34.2,
        34.3,
        34.4,
        34.5,
        34.6,
        34.7,
        34.8,
        34.9,
        35.0,
        35.1,
        35.2,
        35.3,
        35.4,
        35.5,
        35.6,
        35.7,
        35.8,
        35.9,
        36.0,
        36.1,
        36.2,
        36.3,
        36.4,
        36.5,
        36.6,
        36.7,
        36.8,
        36.9,
        37.0,
        37.1,
        37.2,
        37.3,
        37.4,
        37.5,
        37.6,
        37.7,
        37.8,
        37.9,
        38.0,
        38.1,
        38.2,
        38.3,
        38.4,
        38.5,
        38.6,
        38.7,
        38.8,
        38.9,
        39.0,
        39.1,
        39.2,
        39.3,
        39.4,
        39.5,
        39.6,
        39.7,
        39.8,
        39.9,
        40.0,
        40.1,
        40.2,
        40.3,
        40.4,
        40.5,
        40.6,
        40.7,
        40.8,
        40.9,
        41.0,
        41.1,
        41.2,
        41.3,
        41.4,
        41.5,
        41.6,
        41.7,
        41.8,
        41.9,
        42.0,
        42.1,
        42.2,
        42.3,
        42.4,
        42.5,
        42.6,
        42.7,
        42.8,
        42.9,
        43.0,
        43.1,
        43.2,
        43.3,
        43.4,
        43.5,
        43.6,
        43.7,
        43.8,
        43.9,
        44.0,
        44.1,
        44.2,
        44.3,
        44.4,
        44.5,
        44.6,
        44.7,
        44.8,
        44.9,
        45.0,
        45.1,
        45.2,
        45.3,
        45.4,
        45.5,
        45.6,
        45.7,
        45.8,
        45.9,
        46.0,
        46.1,
        46.2,
        46.3,
        46.4,
        46.5,
        46.6,
        46.7,
        46.8,
        46.9,
        47.0,
        47.1,
        47.2,
        47.3,
        47.4,
        47.5,
        47.6,
        47.7,
        47.8,
        47.9,
        48.0,
        48.1,
        48.2,
        48.3,
        48.4,
        48.5,
        48.6,
        48.7,
        48.8,
        48.9,
        49.0,
        49.1,
        49.2,
        49.3,
        49.4,
        49.5,
        49.6,
        49.7,
        49.8,
        49.9,
        50.0,
        50.1,
        50.2,
        50.3,
        50.4,
        50.5,
        50.6,
        50.7,
        50.8,
        50.9,
        51.0,
        51.1,
        51.2,
        51.3,
        51.4,
        51.5,
        51.6,
        51.7,
        51.8,
        51.9,
        52.0,
        52.1,
        52.2,
        52.3,
        52.4,
        52.5,
        52.6,
        52.7,
        52.8,
        52.9,
        53.0,
        53.1,
        53.2,
        53.3,
        53.4,
        53.5,
        53.6,
        53.7,
        53.8,
        53.9,
        54.0,
        54.1,
        54.2,
        54.3,
        54.4,
        54.5,
        54.6,
        54.7,
        54.8,
        54.9,
        55.0,
        55.1,
        55.2,
        55.3,
        55.4,
        55.5,
        55.6,
        55.7,
        55.8,
        55.9,
        56.0,
        56.1,
        56.2,
        56.3,
        56.4,
        56.5,
        56.6,
        56.7,
        56.8,
        56.9,
        57.0,
        57.1,
        57.2,
        57.3,
        57.4,
        57.5,
        57.6,
        57.7,
        57.8,
        57.9,
        58.0,
        58.1,
        58.2,
        58.3,
        58.4,
        58.5,
        58.6,
        58.7,
        58.8,
        58.9,
        59.0,
        59.1,
        59.2,
        59.3,
        59.4,
        59.5,
        59.6,
        59.7,
        59.8,
        59.9,
        60.0,
        60.1,
        60.2,
        60.3,
        60.4,
        60.5,
        60.6,
        60.7,
        60.8,
        60.9,
        61.0,
        61.1,
        61.2,
        61.3,
        61.4,
        61.5,
        61.6,
        61.7,
        61.8,
        61.9,
        62.0,
        62.1,
        62.2,
        62.3,
        62.4,
        62.5,
        62.6,
        62.7,
        62.8,
        62.9,
        63.0,
        63.1,
        63.2,
        63.3,
        63.4,
        63.5,
        63.6,
        63.7,
        63.8,
        63.9,
        64.0,
        64.1,
        64.2,
        64.3,
        64.4,
        64.5,
        64.6,
        64.7,
        64.8,
        64.9,
        65.0,
        65.1,
        65.2,
        65.3,
        65.4,
        65.5,
        65.6,
        65.7,
        65.8,
        65.9,
        66.0,
        66.1,
        66.2,
        66.3,
        66.4,
        66.5,
        66.6,
        66.7,
        66.8,
        66.9,
        67.0,
        67.1,
        67.2,
        67.3,
        67.4,
        67.5,
        67.6,
        67.7,
        67.8,
        67.9,
        68.0,
        68.1,
        68.2,
        68.3,
        68.4,
        68.5,
        68.6,
        68.7,
        68.8,
        68.9,
        69.0,
        69.1,
        69.2,
        69.3,
        69.4,
        69.5,
        69.6,
        69.7,
        69.8,
        69.9,
        70.0,
        70.1,
        70.2,
        70.3,
        70.4,
        70.5,
        70.6,
        70.7,
        70.8,
        70.9,
        71.0,
        71.1,
        71.2,
        71.3,
        71.4,
        71.5,
        71.6,
        71.7,
        71.8,
        71.9,
        72.0,
        72.1,
        72.2,
        72.3,
        72.4,
        72.5,
        72.6,
        72.7,
        72.8,
        72.9,
        73.0,
        73.1,
        73.2,
        73.3,
        73.4,
        73.5,
        73.6,
        73.7,
        73.8,
        73.9,
        74.0,
        74.1,
        74.2,
        74.3,
        74.4,
        74.5,
        74.6,
        74.7,
        74.8,
        74.9,
        75.0,
        75.1,
        75.2,
        75.3,
        75.4,
        75.5,
        75.6,
        75.7,
        75.8,
        75.9,
        76.0,
        76.1,
        76.2,
        76.3,
        76.4,
        76.5,
        76.6,
        76.7,
        76.8,
        76.9,
        77.0,
        77.1,
        77.2,
        77.3,
        77.4,
        77.5,
        77.6,
        77.7,
        77.8,
        77.9,
        78.0,
        78.1,
        78.2,
        78.3,
        78.4,
        78.5,
        78.6,
        78.7,
        78.8,
        78.9,
        79.0,
        79.1,
        79.2,
        79.3,
        79.4,
        79.5,
        79.6,
        79.7,
        79.8,
        79.9,
        80.0,
        80.1,
        80.2,
        80.3,
        80.4,
        80.5,
        80.6,
        80.7,
        80.8,
        80.9,
        81.0,
        81.1,
        81.2,
        81.3,
        81.4,
        81.5,
        81.6,
        81.7,
        81.8,
        81.9,
        82.0,
        82.1,
        82.2,
        82.3,
        82.4,
        82.5,
        82.6,
        82.7,
        82.8,
        82.9,
        83.0,
        83.1,
        83.2,
        83.3,
        83.4,
        83.5,
        83.6,
        83.7,
        83.8,
        83.9,
        84.0,
        84.1,
        84.2,
        84.3,
        84.4,
        84.5,
        84.6,
        84.7,
        84.8,
        84.9,
        85.0,
        85.1,
        85.2,
        85.3,
        85.4,
        85.5,
        85.6,
        85.7,
        85.8,
        85.9,
        86.0,
        86.1,
        86.2,
        86.3,
        86.4,
        86.5,
        86.6,
        86.7,
        86.8,
        86.9,
        87.0,
        87.1,
        87.2,
        87.3,
        87.4,
        87.5,
        87.6,
        87.7,
        87.8,
        87.9,
        88.0,
        88.1,
        88.2,
        88.3,
        88.4,
        88.5,
        88.6,
        88.7,
        88.8,
        88.9,
        89.0,
        89.1,
        89.2,
        89.3,
        89.4,
        89.5,
        89.6,
        89.7,
        89.8,
        89.9,
        90.0,
        90.1,
        90.2,
        90.3,
        90.4,
        90.5,
        90.6,
        90.7,
        90.8,
        90.9,
        91.0,
        91.1,
        91.2,
        91.3,
        91.4,
        91.5,
        91.6,
        91.7,
        91.8,
        91.9,
        92.0,
        92.1,
        92.2,
        92.3,
        92.4,
        92.5,
        92.6,
        92.7,
        92.8,
        92.9,
        93.0,
        93.1,
        93.2,
        93.3,
        93.4,
        93.5,
        93.6,
        93.7,
        93.8,
        93.9,
        94.0,
        94.1,
        94.2,
        94.3,
        94.4,
        94.5,
        94.6,
        94.7,
        94.8,
        94.9,
        95.0,
        95.1,
        95.2,
        95.3,
        95.4,
        95.5,
        95.6,
        95.7,
        95.8,
        95.9,
        96.0,
        96.1,
        96.2,
        96.3,
        96.4,
        96.5,
        96.6,
        96.7,
        96.8,
        96.9,
        97.0,
        97.1,
        97.2,
        97.3,
        97.4,
        97.5,
        97.6,
        97.7,
        97.8,
        97.9,
        98.0,
        98.1,
        98.2,
        98.3,
        98.4,
        98.5,
        98.6,
        98.7,
        98.8,
        98.9,
        99.0,
        99.1,
        99.2,
        99.3,
        99.4,
        99.5,
        99.6,
        99.7,
        99.8,
        99.9
      ],
      "count":[
        0.0,
        0.0,
        0.0,
        0.0,
        0.0,
        0.0,
        0.0,
        0.0,
        0.0,
        0.0,
        0.0,
        0.0,
        0.0,
        0.0,
        0.0,
        0.0,
        0.0,
        0.0,
        0.0,
        0.0,
        0.0,
        0.0,
        0.0,
        0.0,
        0.0,
        0.0,
        0.0,
        0.0,
        0.0,
        0.0,
        0.0,
        0.0,
        0.0,
        0.0,
        0.0,
        0.0,
        0.0,
        0.0,
        0.0,
        0.0,
        0.0,
        0.0,
        0.0,
        0.0,
        0.0,
        0.0,
        0.0,
        0.0,
        0.0,
        0.0,
        0.0,
        0.0,
        0.0,
        0.0,
        0.0,
        0.0,
        0.0,
        0.0,
        0.0,
        0.0,
        0.0,
        0.0,
        0.0,
        0.0,
        0.0,
        0.0,
        0.0,
        0.0,
        0.0,
        0.0,
        0.0,
        0.0,
        0.0,
        0.0,
        0.0,
        0.0,
        0.0,
        0.0,
        0.0,
        0.0,
        0.0,
        0.0,
        0.0,
        0.0,
        0.0,
        0.0,
        0.0,
        0.0,
        0.0,
        0.0,
        0.0,
        0.0,
        0.0,
        0.0,
        0.0,
        0.0,
        0.0,
        0.0,
        0.0,
        0.0,
        0.0,
        0.0,
        0.0,
        0.0,
        0.0,
        0.0,
        0.0,
        0.0,
        0.0,
        0.0,
        0.0,
        0.0,
        0.0,
        0.0,
        0.0,
        0.0,
        0.0,
        0.0,
        0.0,
        0.0,
        0.0,
        0.0,
        0.0,
        0.0,
        0.0,
        0.0,
        0.0,
        0.0,
        0.0,
        0.0,
        0.0,
        0.0,
        0.0,
        0.0,
        0.0,
        0.0,
        0.0,
        0.0,
        0.0,
        0.0,
        0.0,
        0.0,
        0.0,
        0.0,
        0.0,
        0.0,
        0.0,
        0.0,
        0.0,
        0.0,
        0.0,
        0.0,
        0.0,
        0.0,
        0.0,
        0.0,
        0.0,
        0.0,
        0.0,
        0.0,
        0.0,
        0.0,
        0.0,
        0.0,
        0.0,
        0.0,
        0.0,
        0.0,
        0.0,
        0.0,
        0.0,
        0.0,
        0.0,
        0.0,
        0.0,
        0.0,
        0.0,
        1.0,
        0.0,
        1.0,
        0.0,
        0.0,
        1.0,
        0.0,
        0.0,
        0.0,
        0.0,
        0.0,
        0.0,
        0.0,
        0.0,
        0.0,
        0.0,
        0.0,
        1.0,
        1.0,
        0.0,
        0.0,
        0.0,
        0.0,
        0.0,
        0.0,
        0.0,
        0.0,
        0.0,
        0.0,
        0.0,
        0.0,
        0.0,
        0.0,
        0.0,
        0.0,
        2.0,
        0.0,
        0.0,
        0.0,
        0.0,
        0.0,
        0.0,
        0.0,
        0.0,
        1.0,
        1.0,
        0.0,
        0.0,
        0.0,
        2.0,
        0.0,
        1.0,
        0.0,
        0.0,
        1.0,
        0.0,
        0.0,
        0.0,
        0.0,
        0.0,
        0.0,
        0.0,
        0.0,
        1.0,
        0.0,
        1.0,
        0.0,
        0.0,
        0.0,
        0.0,
        0.0,
        1.0,
        0.0,
        1.0,
        1.0,
        0.0,
        0.0,
        3.0,
        1.0,
        1.0,
        0.0,
        1.0,
        2.0,
        0.0,
        0.0,
        0.0,
        0.0,
        1.0,
        0.0,
        1.0,
        2.0,
        2.0,
        0.0,
        1.0,
        0.0,
        2.0,
        2.0,
        1.0,
        0.0,
        0.0,
        0.0,
        0.0,
        1.0,
        0.0,
        0.0,
        0.0,
        1.0,
        0.0,
        0.0,
        0.0,
        1.0,
        1.0,
        1.0,
        1.0,
        1.0,
        0.0,
        1.0,
        2.0,
        0.0,
        0.0,
        0.0,
        0.0,
        0.0,
        0.0,
        0.0,
        0.0,
        0.0,
        1.0,
        0.0,
        0.0,
        0.0,
        1.0,
        0.0,
        1.0,
        1.0,
        2.0,
        2.0,
        0.0,
        2.0,
        1.0,
        1.0,
        1.0,
        0.0,
        1.0,
        1.0,
        0.0,
        1.0,
        1.0,
        0.0,
        1.0,
        1.0,
        2.0,
        0.0,
        0.0,
        2.0,
        2.0,
        0.0,
        1.0,
        1.0,
        3.0,
        2.0,
        2.0,
        0.0,
        3.0,
        0.0,
        2.0,
        1.0,
        1.0,
        0.0,
        2.0,
        2.0,
        1.0,
        0.0,
        1.0,
        1.0,
        0.0,
        1.0,
        3.0,
        0.0,
        2.0,
        1.0,
        2.0,
        3.0,
        1.0,
        1.0,
        5.0,
        1.0,
        0.0,
        1.0,
        3.0,
        1.0,
        5.0,
        3.0,
        2.0,
        8.0,
        11.0,
        20.0,
        31.0,
        27.0,
        29.0,
        53.0,
        26.0,
        0.0,
        5.0,
        0.0,
        3151.0,
        0.0,
        0.0,
        0.0,
        0.0,
        0.0,
        0.0,
        0.0,
        0.0,
        0.0,
        0.0,
        0.0,
        0.0,
        0.0,
        0.0,
        0.0,
        0.0,
        0.0,
        0.0,
        0.0,
        0.0,
        0.0,
        0.0,
        0.0,
        0.0,
        0.0,
        0.0,
        0.0,
        0.0,
        0.0,
        0.0,
        0.0,
        0.0,
        0.0,
        0.0,
        0.0,
        0.0,
        0.0,
        0.0,
        0.0,
        0.0,
        0.0,
        0.0,
        0.0,
        0.0,
        0.0,
        0.0,
        0.0,
        0.0,
        0.0,
        0.0,
        0.0,
        0.0,
        0.0,
        0.0,
        0.0,
        0.0,
        0.0,
        0.0,
        0.0,
        0.0,
        0.0,
        0.0,
        0.0,
        0.0,
        0.0,
        0.0,
        0.0,
        0.0,
        0.0,
        0.0,
        0.0,
        0.0,
        0.0,
        0.0,
        0.0,
        0.0,
        0.0,
        0.0,
        0.0,
        0.0,
        0.0,
        0.0,
        0.0,
        0.0,
        0.0,
        0.0,
        0.0,
        0.0,
        0.0,
        0.0,
        0.0,
        0.0,
        0.0,
        0.0,
        0.0,
        0.0,
        0.0,
        0.0,
        0.0,
        0.0,
        0.0,
        0.0,
        0.0,
        0.0,
        0.0,
        0.0,
        0.0,
        0.0,
        0.0,
        0.0,
        0.0,
        0.0,
        0.0,
        0.0,
        0.0,
        0.0,
        0.0,
        0.0,
        0.0,
        0.0,
        0.0,
        0.0,
        0.0,
        0.0,
        0.0,
        0.0,
        0.0,
        0.0,
        0.0,
        0.0,
        0.0,
        0.0,
        0.0,
        0.0,
        0.0,
        0.0,
        0.0,
        0.0,
        0.0,
        0.0,
        0.0,
        0.0,
        0.0,
        0.0,
        0.0,
        0.0,
        0.0,
        0.0,
        0.0,
        0.0,
        0.0,
        0.0,
        0.0,
        0.0,
        0.0,
        0.0,
        0.0,
        0.0,
        0.0,
        0.0,
        0.0,
        0.0,
        0.0,
        0.0,
        0.0,
        0.0,
        0.0,
        0.0,
        0.0,
        0.0,
        0.0,
        0.0,
        0.0,
        0.0,
        0.0,
        0.0,
        0.0,
        0.0,
        0.0,
        0.0,
        0.0,
        0.0,
        0.0,
        0.0,
        0.0,
        0.0,
        0.0,
        0.0,
        0.0,
        0.0,
        0.0,
        0.0,
        0.0,
        0.0,
        0.0,
        0.0,
        0.0,
        0.0,
        0.0,
        0.0,
        0.0,
        0.0,
        0.0,
        0.0,
        0.0,
        0.0,
        0.0,
        0.0,
        0.0,
        0.0,
        0.0,
        0.0,
        0.0,
        0.0,
        0.0,
        0.0,
        0.0,
        0.0,
        0.0,
        0.0,
        0.0,
        0.0,
        0.0,
        0.0,
        0.0,
        0.0,
        0.0,
        0.0,
        0.0,
        0.0,
        0.0,
        0.0,
        0.0,
        0.0,
        0.0,
        0.0,
        0.0,
        0.0,
        0.0,
        0.0,
        0.0,
        0.0,
        0.0,
        0.0,
        0.0,
        0.0,
        0.0,
        0.0,
        0.0,
        0.0,
        0.0,
        0.0,
        0.0,
        0.0,
        0.0,
        0.0,
        0.0,
        0.0,
        0.0,
        0.0,
        0.0,
        0.0,
        0.0,
        0.0,
        0.0,
        0.0,
        0.0,
        0.0,
        0.0,
        0.0,
        0.0,
        0.0,
        0.0,
        0.0,
        0.0,
        0.0,
        0.0,
        0.0,
        0.0,
        0.0,
        0.0,
        0.0,
        0.0,
        0.0,
        0.0,
        0.0,
        0.0,
        0.0,
        0.0,
        0.0,
        0.0,
        0.0,
        0.0,
        0.0,
        0.0,
        0.0,
        0.0,
        0.0,
        0.0,
        0.0,
        0.0,
        0.0,
        0.0,
        0.0,
        0.0,
        0.0,
        0.0,
        0.0,
        0.0,
        0.0,
        0.0,
        0.0,
        0.0,
        0.0,
        0.0,
        0.0,
        0.0,
        0.0,
        0.0,
        0.0,
        0.0,
        0.0,
        0.0,
        0.0,
        0.0,
        0.0,
        0.0,
        0.0,
        0.0,
        0.0,
        0.0,
        0.0,
        0.0,
        0.0,
        0.0,
        0.0,
        0.0,
        0.0,
        0.0,
        0.0,
        0.0,
        0.0,
        0.0,
        0.0,
        0.0,
        0.0,
        0.0,
        0.0,
        0.0,
        0.0,
        0.0,
        0.0,
        0.0,
        0.0,
        0.0,
        0.0,
        0.0,
        0.0,
        0.0,
        0.0,
        0.0,
        0.0,
        0.0,
        0.0,
        0.0,
        0.0,
        0.0,
        0.0,
        0.0,
        0.0,
        0.0,
        0.0,
        0.0,
        0.0,
        0.0,
        0.0,
        0.0,
        0.0,
        0.0,
        0.0,
        0.0,
        0.0,
        0.0,
        0.0,
        0.0,
        0.0,
        0.0,
        0.0,
        0.0,
        0.0,
        0.0,
        0.0,
        0.0,
        0.0,
        0.0,
        0.0,
        0.0,
        0.0,
        0.0,
        0.0,
        0.0,
        0.0,
        0.0,
        0.0,
        0.0,
        0.0,
        0.0,
        0.0,
        0.0,
        0.0,
        0.0,
        0.0,
        0.0,
        0.0,
        0.0,
        0.0,
        0.0,
        0.0,
        0.0,
        0.0,
        0.0,
        0.0,
        0.0,
        0.0,
        0.0,
        0.0,
        0.0,
        0.0,
        0.0,
        0.0,
        0.0,
        0.0,
        0.0,
        0.0,
        0.0,
        0.0,
        0.0,
        0.0,
        0.0,
        0.0,
        0.0,
        0.0,
        0.0,
        0.0,
        0.0,
        0.0,
        0.0,
        0.0,
        0.0,
        0.0,
        0.0,
        0.0,
        0.0,
        0.0,
        0.0,
        0.0,
        0.0,
        0.0,
        0.0,
        0.0,
        0.0,
        0.0,
        0.0,
        0.0,
        0.0,
        0.0,
        0.0,
        0.0,
        0.0,
        0.0,
        0.0,
        0.0,
        0.0,
        0.0,
        0.0,
        0.0,
        0.0,
        0.0,
        0.0,
        0.0,
        0.0,
        0.0,
        0.0,
        0.0,
        0.0,
        0.0,
        0.0,
        0.0,
        0.0,
        0.0,
        0.0,
        0.0,
        0.0,
        0.0,
        0.0,
        0.0,
        0.0,
        0.0,
        0.0,
        0.0,
        0.0,
        0.0,
        0.0,
        0.0,
        0.0,
        0.0,
        0.0,
        0.0,
        0.0,
        0.0,
        0.0,
        0.0,
        0.0,
        0.0,
        0.0,
        0.0,
        0.0,
        0.0,
        0.0,
        0.0,
        0.0,
        0.0,
        0.0,
        0.0,
        0.0,
        0.0,
        0.0,
        0.0,
        0.0,
        0.0,
        0.0,
        0.0,
        0.0,
        0.0,
        0.0,
        0.0,
        0.0,
        0.0,
        0.0,
        0.0,
        0.0,
        0.0,
        0.0,
        0.0,
        0.0,
        0.0,
        0.0,
        0.0,
        0.0,
        0.0,
        0.0,
        0.0,
        0.0,
        0.0,
        0.0,
        0.0,
        0.0,
        0.0,
        0.0,
        0.0,
        0.0,
        0.0,
        0.0,
        0.0,
        0.0,
        0.0,
        0.0,
        0.0,
        0.0,
        0.0,
        0.0,
        0.0,
        0.0,
        0.0,
        0.0,
        0.0,
        0.0,
        0.0,
        0.0,
        0.0,
        0.0,
        0.0,
        0.0,
        0.0,
        0.0,
        0.0,
        0.0,
        0.0,
        0.0,
        0.0,
        0.0,
        0.0,
        0.0,
        0.0,
        0.0,
        0.0,
        0.0,
        0.0,
        0.0,
        0.0,
        0.0,
        0.0,
        0.0,
        0.0,
        0.0,
        0.0,
        0.0,
        0.0,
        0.0,
        0.0,
        0.0,
        0.0,
        0.0,
        0.0,
        0.0,
        0.0,
        0.0
      ]
    }
  },
  "spectrum":{
    "description":"Information about spectra simulation like DRX, FTIR, ssNMR, UV-VIS, Band dispersion, Phonon dispersion..."
  },
  "experimental":{
    "description":"Experimental data DRX, FTIR, ssNMR, UV-VIS..."
  }
}