{
  "system":{
    "description":"Informations about the system such as name, if it is optimized and other relevant information.",
    "name":"C3_TPTA_CHO_H_H-C2_ANTR_NH2_H_H_H_H-HCB_A-AA",
    "geo_opt":true,
    "opt_type":[
      "OPT_2"
    ],
    "charges":false
  },
  "geometry":{
    "description":"Informations about the geometry: cell parameters, cell matrix, atomic positions, partial charges, bond orders, simmetry information",
    "cell_matrix":[
      [
        47.0246018186,
        0.0,
        0.0
      ],
      [
        23.5686592989,
        40.822115372,
        0.0
      ],
      [
        0.0,
        0.0,
        7.8709641489
      ]
    ],
    "cell_parameters":[
      47.0246018186,
      47.1373185978,
      7.8709641489,
      90.0,
      90.0,
      60.0
    ],
    "atom_labels":[
      "H",
      "H",
      "H",
      "H",
      "H",
      "H",
      "H",
      "H",
      "H",
      "H",
      "H",
      "H",
      "H",
      "H",
      "H",
      "H",
      "H",
      "H",
      "H",
      "H",
      "H",
      "H",
      "H",
      "H",
      "H",
      "H",
      "H",
      "H",
      "H",
      "H",
      "H",
      "H",
      "H",
      "H",
      "H",
      "H",
      "H",
      "H",
      "H",
      "H",
      "H",
      "H",
      "H",
      "H",
      "H",
      "H",
      "H",
      "H",
      "H",
      "H",
      "H",
      "H",
      "H",
      "H",
      "H",
      "H",
      "H",
      "H",
      "H",
      "H",
      "H",
      "H",
      "H",
      "H",
      "H",
      "H",
      "H",
      "H",
      "H",
      "H",
      "H",
      "H",
      "H",
      "H",
      "H",
      "H",
      "H",
      "H",
      "H",
      "H",
      "H",
      "H",
      "H",
      "H",
      "H",
      "H",
      "H",
      "H",
      "H",
      "H",
      "H",
      "H",
      "H",
      "H",
      "H",
      "H",
      "H",
      "H",
      "H",
      "H",
      "H",
      "H",
      "H",
      "H",
      "H",
      "H",
      "H",
      "H",
      "C",
      "C",
      "C",
      "C",
      "C",
      "C",
      "C",
      "C",
      "C",
      "C",
      "C",
      "C",
      "C",
      "C",
      "C",
      "C",
      "C",
      "C",
      "C",
      "C",
      "C",
      "C",
      "C",
      "C",
      "C",
      "C",
      "C",
      "C",
      "C",
      "C",
      "C",
      "C",
      "C",
      "C",
      "C",
      "C",
      "C",
      "C",
      "C",
      "C",
      "C",
      "C",
      "C",
      "C",
      "C",
      "C",
      "C",
      "C",
      "C",
      "C",
      "C",
      "C",
      "C",
      "C",
      "C",
      "C",
      "C",
      "C",
      "C",
      "C",
      "C",
      "C",
      "C",
      "C",
      "C",
      "C",
      "C",
      "C",
      "C",
      "C",
      "C",
      "C",
      "C",
      "C",
      "C",
      "C",
      "C",
      "C",
      "C",
      "C",
      "C",
      "C",
      "C",
      "C",
      "C",
      "C",
      "C",
      "C",
      "C",
      "C",
      "C",
      "C",
      "C",
      "C",
      "C",
      "C",
      "C",
      "C",
      "C",
      "C",
      "C",
      "C",
      "C",
      "C",
      "C",
      "C",
      "C",
      "C",
      "C",
      "C",
      "C",
      "C",
      "C",
      "C",
      "C",
      "C",
      "C",
      "C",
      "C",
      "C",
      "C",
      "C",
      "C",
      "C",
      "C",
      "C",
      "C",
      "C",
      "C",
      "C",
      "C",
      "C",
      "C",
      "C",
      "C",
      "C",
      "C",
      "C",
      "C",
      "C",
      "C",
      "C",
      "C",
      "C",
      "C",
      "C",
      "C",
      "C",
      "C",
      "C",
      "C",
      "C",
      "C",
      "C",
      "C",
      "C",
      "C",
      "C",
      "C",
      "C",
      "C",
      "C",
      "C",
      "C",
      "C",
      "C",
      "C",
      "C",
      "C",
      "C",
      "C",
      "C",
      "C",
      "C",
      "C",
      "C",
      "C",
      "C",
      "C",
      "C",
      "N",
      "N",
      "N",
      "N",
      "N",
      "N",
      "N",
      "N",
      "N",
      "N",
      "N",
      "N",
      "N",
      "N",
      "N",
      "N",
      "N",
      "N",
      "N",
      "N",
      "N",
      "N",
      "N",
      "N",
      "O",
      "O",
      "O",
      "O",
      "O",
      "O",
      "O",
      "O",
      "O",
      "O",
      "O",
      "O"
    ],
    "atom_pos":[
      [
        32.552652206,
        21.6818236674,
        3.9089532534
      ],
      [
        32.5432352291,
        21.0224567573,
        7.4686872164
      ],
      [
        30.794546406,
        20.006492221,
        3.4664219714
      ],
      [
        30.7872531862,
        19.3242555218,
        7.0669686295
      ],
      [
        29.5909805444,
        19.0469119017,
        1.5385540138
      ],
      [
        29.6122941932,
        18.1940308915,
        5.242439477
      ],
      [
        33.5795885458,
        17.5840762325,
        1.2579490626
      ],
      [
        33.622228092,
        16.7834752321,
        5.071249162
      ],
      [
        -7.0221880597,
        20.7766858424,
        1.0474221888
      ],
      [
        -7.0270791459,
        20.0685633018,
        4.6896137144
      ],
      [
        -8.7745322957,
        19.0898608392,
        0.7109391994
      ],
      [
        -8.7602094232,
        18.3712576992,
        4.3725835269
      ],
      [
        -6.1376731685,
        22.6054236252,
        0.7168175485
      ],
      [
        -6.0861327357,
        21.7805427995,
        4.4755676255
      ],
      [
        -9.7684527586,
        23.2795271126,
        3.2232377038
      ],
      [
        -9.7758700857,
        22.5577361144,
        6.8838802849
      ],
      [
        -12.1312861222,
        22.4872864117,
        3.5775737578
      ],
      [
        -12.1355333217,
        21.7785904693,
        7.2031016857
      ],
      [
        35.910659771,
        18.3638871148,
        0.9530623102
      ],
      [
        35.9434146828,
        17.5963837466,
        4.6886463386
      ],
      [
        25.8693849218,
        2.2375468101,
        0.2636484979
      ],
      [
        25.8845225559,
        1.3062521413,
        4.0016404905
      ],
      [
        25.3320470655,
        4.6141868281,
        0.709561624
      ],
      [
        25.2614816064,
        3.6662024587,
        4.3661396089
      ],
      [
        24.939341754,
        6.2025575057,
        2.4795095192
      ],
      [
        24.973718497,
        5.2500031447,
        6.1450393746
      ],
      [
        21.646350541,
        3.4747790393,
        2.6107724029
      ],
      [
        21.762597803,
        2.4625402929,
        6.5601222364
      ],
      [
        -2.211879136,
        37.132606576,
        3.0384384667
      ],
      [
        -2.0272112548,
        36.1079663901,
        6.8788021658
      ],
      [
        -2.8109169997,
        39.4888585652,
        3.3219799161
      ],
      [
        -2.6216384742,
        38.4639498425,
        7.2396588645
      ],
      [
        -1.2949415846,
        35.3617680617,
        3.0721497045
      ],
      [
        -0.9077353726,
        34.3894976608,
        7.0780414343
      ],
      [
        1.3081518391,
        38.2349509836,
        0.8116638099
      ],
      [
        1.4612002034,
        37.2754389139,
        4.6380140901
      ],
      [
        1.8461712622,
        40.6541574231,
        0.4963328952
      ],
      [
        1.9559680304,
        39.7070001564,
        4.3217266194
      ],
      [
        21.1454789356,
        1.0664200143,
        2.9735499122
      ],
      [
        21.3220737488,
        0.045847917,
        6.9389562961
      ],
      [
        3.1561094149,
        26.8733579246,
        3.7185096552
      ],
      [
        3.3035788976,
        25.9348706364,
        7.2781046861
      ],
      [
        5.5500438169,
        26.2396117915,
        3.4531343891
      ],
      [
        5.7066039581,
        25.3347438625,
        7.1493595699
      ],
      [
        1.9961897746,
        23.4095271853,
        1.4515973959
      ],
      [
        2.3241241261,
        22.4875352557,
        4.8998249593
      ],
      [
        4.4122264811,
        22.7413934532,
        1.2215250406
      ],
      [
        4.7600442461,
        21.8539788904,
        4.8104674791
      ],
      [
        -2.3044765184,
        25.3256428267,
        0.4782528098
      ],
      [
        -2.1842325428,
        24.3644619497,
        4.1520311008
      ],
      [
        -3.930296114,
        23.4638507624,
        0.3682580309
      ],
      [
        -3.8955578161,
        22.5549307677,
        4.0958824298
      ],
      [
        -4.9635976061,
        27.4988231239,
        3.0733992302
      ],
      [
        -4.8100201706,
        26.7547315108,
        6.5777527212
      ],
      [
        -6.5992921316,
        25.5837681492,
        2.9945093906
      ],
      [
        -6.538058965,
        24.9283253045,
        6.5217843865
      ],
      [
        -1.0194044224,
        30.6948007921,
        3.0940096775
      ],
      [
        -0.6461516052,
        29.7096541459,
        6.9982357763
      ],
      [
        -1.6913339115,
        33.0575778801,
        3.3311078091
      ],
      [
        -1.287533471,
        32.0619349682,
        7.3441407437
      ],
      [
        2.3128093439,
        31.8925399953,
        0.6459407098
      ],
      [
        2.4979535136,
        30.9575808928,
        4.3269853356
      ],
      [
        1.6307980939,
        34.2994379198,
        0.9003894903
      ],
      [
        1.8020291511,
        33.3531921412,
        4.6428205967
      ],
      [
        20.108134507,
        14.6010619388,
        0.6976489968
      ],
      [
        20.3687232231,
        13.7823086191,
        4.3714037205
      ],
      [
        17.680400435,
        15.0878469595,
        0.7147749851
      ],
      [
        17.9399784226,
        14.3439071445,
        4.4276106558
      ],
      [
        20.82657021,
        18.1288857266,
        3.0574313934
      ],
      [
        21.2416500415,
        17.3447851099,
        6.6137745599
      ],
      [
        18.3653144647,
        18.6425619852,
        3.0347059385
      ],
      [
        18.7910576676,
        17.9425780512,
        6.6219035957
      ],
      [
        25.6449151316,
        16.6139450578,
        0.4292578603
      ],
      [
        25.7854827967,
        15.485258105,
        4.3322688723
      ],
      [
        27.433450388,
        18.3298419018,
        0.6726306849
      ],
      [
        27.4842882998,
        17.282859143,
        4.4027413751
      ],
      [
        28.255541339,
        13.6696636908,
        2.1567742884
      ],
      [
        28.4080047913,
        12.9171639171,
        6.5758496516
      ],
      [
        30.0755418,
        15.388456691,
        2.3644347339
      ],
      [
        30.1403109796,
        14.7431752571,
        6.6316206873
      ],
      [
        24.5551518,
        10.8400299786,
        3.5437567509
      ],
      [
        24.6122952734,
        9.8432849624,
        7.3824992789
      ],
      [
        25.2495873698,
        8.4611605708,
        3.3873799352
      ],
      [
        25.2998593749,
        7.4657645659,
        7.1182432653
      ],
      [
        20.9383837995,
        9.9304749848,
        1.4034358608
      ],
      [
        20.9618383024,
        9.0132663638,
        5.2730521772
      ],
      [
        21.6394908804,
        7.5140998814,
        1.2523031843
      ],
      [
        21.6207002993,
        6.590761105,
        5.0709051926
      ],
      [
        11.6576000654,
        17.4619326506,
        3.2389070478
      ],
      [
        12.1465852136,
        16.7433677226,
        7.4322253898
      ],
      [
        14.0585585267,
        16.8939415474,
        3.1047547091
      ],
      [
        14.5247809426,
        16.1370830613,
        7.1075186451
      ],
      [
        15.7701037034,
        16.4251068799,
        1.430625466
      ],
      [
        16.0885887843,
        15.6958161006,
        5.3061932907
      ],
      [
        14.864934315,
        20.5519755427,
        0.9898499906
      ],
      [
        15.2533571322,
        19.8536621734,
        5.0713007655
      ],
      [
        8.7889532152,
        24.4231019985,
        0.5246767588
      ],
      [
        9.0914179128,
        23.5294045776,
        4.4576947035
      ],
      [
        11.1305821579,
        23.7364751174,
        0.1140691763
      ],
      [
        11.4854452854,
        22.9584661019,
        4.2186856847
      ],
      [
        7.2865640089,
        24.8469270449,
        2.4511299429
      ],
      [
        7.5128113209,
        23.9855154803,
        6.2707778526
      ],
      [
        7.9679979223,
        20.6631613218,
        2.4447465679
      ],
      [
        8.3685595787,
        19.8661488825,
        6.59200689
      ],
      [
        9.8138752507,
        19.0472085507,
        2.8156176926
      ],
      [
        10.2697919153,
        18.3150828168,
        7.0496099623
      ],
      [
        12.980289935,
        22.1105095344,
        0.4670128559
      ],
      [
        13.3587059847,
        21.4009883507,
        4.6271885409
      ],
      [
        32.7718938949,
        20.807921415,
        3.2982381936
      ],
      [
        32.768695227,
        20.1206744619,
        6.9017111386
      ],
      [
        31.7910984362,
        19.8781179942,
        3.0482322053
      ],
      [
        31.7926234782,
        19.1807022941,
        6.6767750352
      ],
      [
        29.9076815606,
        18.0060747616,
        1.7156806207
      ],
      [
        29.9400718542,
        17.1855420637,
        5.5419712375
      ],
      [
        33.3663658731,
        18.4850908888,
        1.8299672133
      ],
      [
        33.3935151639,
        17.7252531545,
        5.5655761138
      ],
      [
        32.0768745675,
        18.6914786541,
        2.2959965749
      ],
      [
        32.1000343623,
        17.9511618771,
        6.0121685105
      ],
      [
        -8.0206102905,
        20.9516005549,
        1.4413824242
      ],
      [
        -8.0241139336,
        20.2440434863,
        5.0852543136
      ],
      [
        -8.9939165096,
        20.005046622,
        1.2588026939
      ],
      [
        -8.9881292259,
        19.2886716505,
        4.9116916224
      ],
      [
        -6.3390722149,
        23.3089119485,
        1.5389196162
      ],
      [
        -6.311754415,
        22.5425557739,
        5.2341992403
      ],
      [
        -9.5712949157,
        22.3598493022,
        2.6760792624
      ],
      [
        -9.5751089193,
        21.6459967802,
        6.3237014067
      ],
      [
        -8.3070423802,
        22.1767807369,
        2.1294588704
      ],
      [
        -8.3107343744,
        21.4667208651,
        5.7829563739
      ],
      [
        -11.9086066394,
        21.5860236748,
        3.008519648
      ],
      [
        -11.9101375077,
        20.8753861801,
        6.6375937299
      ],
      [
        -10.6080847872,
        21.3998795798,
        2.5011545855
      ],
      [
        -10.6106281361,
        20.6861914024,
        6.1390734971
      ],
      [
        34.1002601871,
        20.6408595879,
        2.7946680317
      ],
      [
        34.100152559,
        19.9295529131,
        6.4254719922
      ],
      [
        35.6934701747,
        19.2545787952,
        1.5413779531
      ],
      [
        35.7115792531,
        18.5113818057,
        5.2317467726
      ],
      [
        -10.317875748,
        20.1937773011,
        1.7605451569
      ],
      [
        -10.3138727412,
        19.4711476093,
        5.4148001067
      ],
      [
        34.394108235,
        19.4418910726,
        2.0429466945
      ],
      [
        34.4067251544,
        18.705507975,
        5.7218343746
      ],
      [
        24.9676604205,
        2.505410693,
        0.8120430548
      ],
      [
        25.005490803,
        1.5544050164,
        4.5932716114
      ],
      [
        24.6688042264,
        3.8241603241,
        1.057147472
      ],
      [
        24.6644686516,
        2.8679342441,
        4.802925514
      ],
      [
        23.8908344965,
        6.428975097,
        2.2252604653
      ],
      [
        23.909278714,
        5.4663212576,
        5.9621481503
      ],
      [
        22.5737763608,
        3.1886104044,
        2.1190359329
      ],
      [
        22.6655676568,
        2.1961331559,
        6.0140440978
      ],
      [
        23.4448376803,
        4.1867017673,
        1.7092934692
      ],
      [
        23.4748679835,
        3.2105949322,
        5.5241730243
      ],
      [
        -1.5681406597,
        37.9006968695,
        2.6170738365
      ],
      [
        -1.39119706,
        36.8922581347,
        6.4749591641
      ],
      [
        -1.9065355692,
        39.2181508828,
        2.7797401517
      ],
      [
        -1.7283860689,
        38.2061271181,
        6.6731020821
      ],
      [
        -0.500660236,
        35.2242056151,
        2.3250682672
      ],
      [
        -0.2178176326,
        34.2470947776,
        6.2320116037
      ],
      [
        0.424069956,
        38.5275388625,
        1.375331725
      ],
      [
        0.5788668803,
        37.5543123404,
        5.210710756
      ],
      [
        -0.3761512787,
        37.527657724,
        1.9080845324
      ],
      [
        -0.2044191386,
        36.5420941854,
        5.7475028719
      ],
      [
        0.9496961453,
        40.9245137025,
        1.0530537875
      ],
      [
        1.068759184,
        39.9616906083,
        4.8990948997
      ],
      [
        0.1198286403,
        39.9050883584,
        1.5503617882
      ],
      [
        0.2651476753,
        38.9266648921,
        5.408852672
      ],
      [
        24.1080811185,
        1.4565592325,
        1.2605343885
      ],
      [
        24.2038627513,
        0.4888312011,
        5.106739094
      ],
      [
        22.0529158771,
        0.7958352443,
        2.4356744058
      ],
      [
        22.2096858154,
        -0.2080718961,
        6.3607641074
      ],
      [
        -1.0824755836,
        40.2675501475,
        2.2654393098
      ],
      [
        -0.9209148035,
        39.2681113489,
        6.159850363
      ],
      [
        22.8919006869,
        1.8166699746,
        1.9529248975
      ],
      [
        23.008436905,
        0.8283629454,
        5.8449069154
      ],
      [
        0.4994360921,
        26.577311234,
        2.355226944
      ],
      [
        0.6943148117,
        25.6054949344,
        5.9436113484
      ],
      [
        3.4355182732,
        25.984212596,
        3.1639439734
      ],
      [
        3.6192733191,
        25.0550045579,
        6.7290446906
      ],
      [
        4.7744903761,
        25.6136503722,
        3.0143729035
      ],
      [
        4.9698388731,
        24.7104038836,
        6.6459121436
      ],
      [
        5.1376802724,
        24.4441023704,
        2.3241299466
      ],
      [
        5.3921619216,
        23.54899313,
        5.9792934906
      ],
      [
        2.792941379,
        23.9999879312,
        1.8973665643
      ],
      [
        3.0828310069,
        23.0863763563,
        5.3961452334
      ],
      [
        4.12634653,
        23.6352295268,
        1.7715227866
      ],
      [
        4.4287210061,
        22.7419918056,
        5.3444608464
      ],
      [
        2.4635513133,
        25.1749772911,
        2.5762890552
      ],
      [
        2.6892131984,
        24.2345246937,
        6.0911240827
      ],
      [
        -1.4267863797,
        27.6171183822,
        1.9269329637
      ],
      [
        -1.2228312371,
        26.6815331675,
        5.5524885324
      ],
      [
        -3.2317094391,
        25.3773538199,
        1.0415542123
      ],
      [
        -3.1237362443,
        24.4698072893,
        4.6854165132
      ],
      [
        -4.15285084,
        24.3326561448,
        0.9857627271
      ],
      [
        -4.0921547805,
        23.4670580141,
        4.6575239806
      ],
      [
        -5.3745884829,
        24.3973491316,
        1.6808307811
      ],
      [
        -5.3259287336,
        23.6138070937,
        5.323606269
      ],
      [
        -4.7548976159,
        26.5983687858,
        2.5016701161
      ],
      [
        -4.628954535,
        25.824858848,
        6.0440772282
      ],
      [
        -5.6581111099,
        25.5423657077,
        2.4507736744
      ],
      [
        -5.5832539704,
        24.812725118,
        6.0125832518
      ],
      [
        -3.5538495811,
        26.5047418415,
        1.7922546926
      ],
      [
        -3.4079601488,
        25.6399598595,
        5.3889642233
      ],
      [
        0.4967412302,
        28.7489873454,
        1.8460703677
      ],
      [
        0.7083836618,
        27.8023938121,
        5.5452925264
      ],
      [
        -0.4536762659,
        31.4706600199,
        2.591240709
      ],
      [
        -0.119543718,
        30.4943768499,
        6.4665872274
      ],
      [
        -0.8214620655,
        32.8086239096,
        2.7257291452
      ],
      [
        -0.478445137,
        31.8269075947,
        6.6536470442
      ],
      [
        -0.0805590108,
        33.8425455821,
        2.1249825386
      ],
      [
        0.1988654308,
        32.8690629764,
        5.99453975
      ],
      [
        1.439302022,
        32.1729994124,
        1.2294887566
      ],
      [
        1.6640369862,
        31.2221746029,
        4.9722551665
      ],
      [
        1.0612968499,
        33.5028573846,
        1.3744385922
      ],
      [
        1.2810234394,
        32.5467573792,
        5.1546966713
      ],
      [
        0.678620393,
        31.1657009035,
        1.8347447957
      ],
      [
        0.9496635657,
        30.2072939877,
        5.6186749943
      ],
      [
        22.6797046177,
        15.1035278903,
        1.8581379146
      ],
      [
        22.8923533357,
        14.1445712934,
        5.6983604765
      ],
      [
        19.7295738181,
        15.4725915394,
        1.2224513827
      ],
      [
        20.0132719424,
        14.6660212289,
        4.8909936768
      ],
      [
        18.362210086,
        15.7564752973,
        1.2381394028
      ],
      [
        18.6590862111,
        14.9964861607,
        4.9206675361
      ],
      [
        17.859774618,
        16.9174857334,
        1.8516006273
      ],
      [
        18.2120294325,
        16.174605189,
        5.5418734042
      ],
      [
        20.1212737374,
        17.4842537459,
        2.5393224512
      ],
      [
        20.4982909498,
        16.7102881663,
        6.1374991911
      ],
      [
        18.7592317569,
        17.7661304096,
        2.5250623325
      ],
      [
        19.1500408644,
        17.036104707,
        6.1401926003
      ],
      [
        20.5973693531,
        16.3529438725,
        1.8691817115
      ],
      [
        20.9092839213,
        15.5233500919,
        5.5278157655
      ],
      [
        24.628440769,
        14.0522652967,
        1.5410651074
      ],
      [
        24.8346938753,
        13.0488596535,
        5.6071137821
      ],
      [
        26.6077238783,
        16.3530908204,
        0.8537084215
      ],
      [
        26.7327899157,
        15.3192831961,
        4.8289660089
      ],
      [
        27.6236823891,
        17.3070035289,
        0.9959818152
      ],
      [
        27.6943175164,
        16.3305793647,
        4.8879550189
      ],
      [
        28.8783109095,
        16.9779482173,
        1.5400298917
      ],
      [
        28.9302088496,
        16.1290647964,
        5.5204289647
      ],
      [
        28.1059540651,
        14.6929595531,
        1.8211188758
      ],
      [
        28.2354802603,
        13.8757093638,
        6.0939322573
      ],
      [
        29.1087905102,
        15.6452738487,
        1.9363299902
      ],
      [
        29.1872074826,
        14.8851689155,
        6.1278677677
      ],
      [
        26.8559838383,
        15.0544136887,
        1.3012831543
      ],
      [
        27.0155242409,
        14.0984862748,
        5.4448007178
      ],
      [
        22.8323912056,
        12.9043051922,
        2.2080245803
      ],
      [
        22.9563703534,
        11.9570036318,
        6.1282878198
      ],
      [
        23.9253012595,
        10.1164807157,
        3.0394339414
      ],
      [
        23.9740367727,
        9.1380278513,
        6.860771326
      ],
      [
        24.3073706962,
        8.7772894023,
        2.9422828192
      ],
      [
        24.3464798017,
        7.7991624106,
        6.7097317725
      ],
      [
        23.4822189256,
        7.830150315,
        2.3138934454
      ],
      [
        23.5039267818,
        6.8682982394,
        6.0768793569
      ],
      [
        21.8695327831,
        9.5822061399,
        1.8430020367
      ],
      [
        21.8992943952,
        8.6453400502,
        5.6813763418
      ],
      [
        22.2590144226,
        8.2513400484,
        1.7588915209
      ],
      [
        22.2671714717,
        7.3100688686,
        5.5687312098
      ],
      [
        22.7066883109,
        10.4994903911,
        2.4828528793
      ],
      [
        22.7573190925,
        9.5478381711,
        6.3158500015
      ],
      [
        12.3489521666,
        18.1184911441,
        2.713591563
      ],
      [
        12.8135572045,
        17.4040894116,
        6.8816840375
      ],
      [
        13.6800545355,
        17.7986288539,
        2.6332580699
      ],
      [
        14.1320545365,
        17.0677111091,
        6.7022047492
      ],
      [
        16.4343499721,
        17.2402598178,
        1.7587162682
      ],
      [
        16.7905318024,
        16.5000275381,
        5.5776951253
      ],
      [
        14.1519756731,
        19.8798635629,
        1.4630391489
      ],
      [
        14.5603650618,
        19.1800055503,
        5.5715732957
      ],
      [
        14.6120142,
        18.6881996621,
        2.0039865389
      ],
      [
        15.03148962,
        17.9644242334,
        6.0384346654
      ],
      [
        9.1515967518,
        23.4617134329,
        0.8842042003
      ],
      [
        9.4891969992,
        22.6230371483,
        4.9094651453
      ],
      [
        10.4525898868,
        23.0806550738,
        0.6576558599
      ],
      [
        10.8157770549,
        22.3032348084,
        4.7735311849
      ],
      [
        6.5458957673,
        24.0803481884,
        2.1722537485
      ],
      [
        6.8101448576,
        23.1938098669,
        5.9680908112
      ],
      [
        8.6711115338,
        21.3285596423,
        1.9477064978
      ],
      [
        9.0627146304,
        20.538215983,
        6.09182763
      ],
      [
        8.2336985865,
        22.5803364507,
        1.5452126586
      ],
      [
        8.585172036,
        21.7337176172,
        5.5784085156
      ],
      [
        10.5017206513,
        19.7082728233,
        2.2902124537
      ],
      [
        10.9432513517,
        18.9874316556,
        6.5202963877
      ],
      [
        10.0259960975,
        20.9342429942,
        1.7947174499
      ],
      [
        10.4381271694,
        20.1908882926,
        5.9971250115
      ],
      [
        11.8460719249,
        19.3381704175,
        2.1665295344
      ],
      [
        12.2905175432,
        18.6326485163,
        6.3749687979
      ],
      [
        12.2901945621,
        21.4436507605,
        0.9817933391
      ],
      [
        12.6879838895,
        20.7362772726,
        5.1696941022
      ],
      [
        10.948369295,
        21.8244353517,
        1.1259525246
      ],
      [
        11.3411056643,
        21.0883684606,
        5.3101339558
      ],
      [
        12.7739685354,
        20.2312885508,
        1.5076711388
      ],
      [
        13.1917990109,
        19.5325823789,
        5.6905514312
      ],
      [
        31.119756176,
        17.7030904546,
        2.0456902837
      ],
      [
        31.1602525518,
        16.9284481085,
        5.8706669352
      ],
      [
        -7.3853136319,
        23.2211429647,
        2.2964714438
      ],
      [
        -7.3824315558,
        22.5056873255,
        5.9628216574
      ],
      [
        23.0473903049,
        5.5126053685,
        1.8931837496
      ],
      [
        23.0558676647,
        4.5335258174,
        5.7008443578
      ],
      [
        0.0429322759,
        36.2087667574,
        1.6848434972
      ],
      [
        0.2216749444,
        35.2281519982,
        5.512446828
      ],
      [
        1.2387841234,
        27.6641591015,
        2.1322988749
      ],
      [
        1.4344203191,
        26.7022542835,
        5.7941231955
      ],
      [
        -0.8402789934,
        26.4859115321,
        2.3147819257
      ],
      [
        -0.648530395,
        25.5275865925,
        5.8962044798
      ],
      [
        -0.8227270842,
        28.7876975381,
        1.6674411194
      ],
      [
        -0.6084790995,
        27.8639620991,
        5.3587685854
      ],
      [
        22.0558027113,
        13.9994609679,
        2.2578794719
      ],
      [
        22.2017893916,
        13.0734936794,
        6.085935171
      ],
      [
        23.9788075431,
        15.2159343049,
        1.516951098
      ],
      [
        24.2106435712,
        14.2107153844,
        5.4559203445
      ],
      [
        24.1073384921,
        12.8425714705,
        1.8291856701
      ],
      [
        24.2669326938,
        11.8673584856,
        5.9040028344
      ],
      [
        15.9879602221,
        18.4275226154,
        2.0003492928
      ],
      [
        16.3908989703,
        17.6849708492,
        5.8961281142
      ],
      [
        6.8917823164,
        22.9068761322,
        1.7612111612
      ],
      [
        7.2147385886,
        22.0066171563,
        5.6630012826
      ],
      [
        1.0772024106,
        25.4000982669,
        2.6894014537
      ],
      [
        1.2895063379,
        24.4111420395,
        6.1665076579
      ],
      [
        -2.7669359194,
        27.6726770126,
        1.7705823437
      ],
      [
        -2.562459199,
        26.7660060225,
        5.3833380666
      ],
      [
        1.2320207902,
        29.8775705994,
        1.7101791039
      ],
      [
        1.4742148778,
        28.9154683106,
        5.4471309495
      ],
      [
        22.0033866421,
        16.2724745283,
        1.7737908962
      ],
      [
        22.2989019614,
        15.3415739518,
        5.5065815278
      ],
      [
        25.9502340762,
        13.9760226969,
        1.2418322505
      ],
      [
        26.1741905414,
        12.9667339168,
        5.4433936992
      ],
      [
        22.1697588766,
        11.796228421,
        2.6179523389
      ],
      [
        22.2339397701,
        10.8527845446,
        6.4302321427
      ]
    ],
    "energy":-1519.0835381656127,
    "band_gap":1.404849,
    "fermi_level":-3.006999,
    "density":0.30760519971440875,
    "composition":"H108 C180 N24 O12"
  },
  "optimization":{
    "description":"Information about the optimization process such as level of calculations, optimization schema and optimization steps."
  },
  "adsorption":{
    "description":"Information about the adsorption simulation experiments on RASPA2"
  },
  "textural":{
    "description":"Information about the textural calculations of the structure such as specific area, pore volume, void fraction."
  },
  "spectrum":{
    "description":"Information about spectra simulation like DRX, FTIR, ssNMR, UV-VIS, Band dispersion, Phonon dispersion..."
  }
}